Ch03-ModelingBasics/Mux/multiplexer.v

// Structure model of a 2-1 multiplexer
//    
module and_gate(output a, input b, c);
assign a = b & c;
endmodule

module not_gate(output d, input e);
assign d = ~ e;
endmodule

module or_gate(output l, input m, n);
assign l = m | n;
endmodule

module mux21_st(Y, D0, D1, S);
   output Y;
   input  D0, D1, S;
   wire   T1, T2, T3;
   and_gate u1(T1, D1, S);
   not_gate u2(T2, S);
   and_gate u3(T3, D0, T2);
   or_gate u4(Y, T1, T3);
endmodule

// Behavior model:
module mux21_bh(Y, D0, D1, S);
   input wire D0, D1, S;
   output reg Y;

   always @(D0 or D1 or S)
     begin

	if(S) 
	  Y= D1;
	else
	  Y=D0;

     end

endmodule // mux21_bh

// Dataflow model:
module mux21_df(Y, D0, D1, S);

   output Y;
   input  D0, D1, S;

   assign Y=(S)?D1:D0;

endmodule

Ch03-ModelingBasics/Mux/multiplexer_tbtv.v

`timescale 100ps/10ps      // Unit of time is 100ps

module multiplexer_tbtv();
   reg d0, d1, sel;        // Input and
   wire y;                 // Output of DuT
   reg 	yexpct;            // Expected response
    
   reg clk, reset;         // clock and reset are internal

   reg[31:0] vectornum, errors;   // bookkeeping variables
   reg[3:0]  testvectors[10000:0];// array of testvectors
   
   // Instantiate designs under test:
   mux21_bh dut_bh (.Y(y), .D0(d0), .D1(d1), .S(sel));
   //  mux21_st dut_st (.Y(y_st), .D0(d0), .D1(d1), .S(sel));
   //  mux21_df dut_df (.Y(y_df), .D0(d0), .D1(d1), .S(sel));

   // generate clock
   always     // no sensitivity list
     begin
	clk= 1; #5; 
	clk= 0; #5;  // 1ns period
     end

   initial           
     begin
	$dumpfile("multiplexer.vcd"); // File with simulation results
	$dumpvars(0,multiplexer_tbtv); // which variables are written to file
	$readmemb("multiplexer.tv", testvectors); // Read vectors
	vectornum= 0; errors = 0;                 // Initialize
	reset = 1; 
	#27; reset = 0;                           // Apply reset wait
     end

   // Stimuli generation:
   // apply test vectors on rising edge of clk
   always @(posedge clk)
     begin
	#1; {d0,d1,sel, yexpct} = testvectors[vectornum];
     end

   // Response checker:
   // check results on falling edge of clk
   always @(negedge clk)
     if (~reset)               // skip during reset
       begin 
	  if (y !== yexpct) 
	    begin
	       $display("Error: inputs = %b", {d0,d1,sel});
	       $display("  outputs = %b (%b exp)",y,yexpct);
	       errors = errors + 1;
	    end

	  // increment array index and read next testvector
	  vectornum = vectornum + 1;
	  if (testvectors[vectornum] ===4'bx)
	    begin 
	       $display("%d tests completed with %d errors", vectornum, errors);
	       $finish;// End simulation 
	    end
       end
endmodule

Ch03-ModelingBasics/Mux/multiplexer.vcd
$date
	Tue Apr  7 13:49:26 2020
$end
$version
	Icarus Verilog
$end
$timescale
	10ps
$end
$scope module multiplexer_tbtv $end
$var wire 1 ! y $end
$var reg 1 " clk $end
$var reg 1 # d0 $end
$var reg 1 $ d1 $end
$var reg 32 % errors [31:0] $end
$var reg 1 & reset $end
$var reg 1 ' sel $end
$var reg 32 ( vectornum [31:0] $end
$var reg 1 ) yexpct $end
$scope module dut_bh $end
$var wire 1 # D0 $end
$var wire 1 $ D1 $end
$var wire 1 ' S $end
$var reg 1 ! Y $end
$upscope $end
$upscope $end
$enddefinitions $end
#0
$dumpvars
x)
b0 (
x'
1&
b0 %
x$
x#
1"
x!
$end
#50
0"
#100
1"
#110
0!
0#
0$
0'
0)
#150
0"
#200
1"
#250
0"
#270
0&
#300
1"
#350
b1 (
0"
#400
1"
#410
1'
#450
b10 (
0"
#500
1"
#510
1$
0'
#550
b11 (
0"
#600
1"
#610
1!
1'
1)
#650
b100 (
0"
#700
1"
#710
1#
0$
0'
#750
b101 (
0"
#800
1"
#810
0!
1'
0)
#850
b110 (
0"
#900
1"
#910
1!
1$
0'
1)
#950
b111 (
0"
#1000
1"
#1010
1'
#1050
b1000 (
0"
