Ch08-Datapath/ThreeStateBus/BusUser.v
// This is a Verilog description for a 3-state bus

`timescale 1ns / 100ps

module BusUser (en, clk, dbus);
   parameter width = 4;  // Bit width of bus

   input en, clk;
   inout [width-1:0] dbus;  // Bus lines

   reg [width-1:0]   indata, outdata; // Connection to bus
   reg [width-1:0]   private = {width{1'b0}};
   
   always @(posedge clk) begin
      if (en) 
	outdata <= private;            // Drive the bus
      else    
	outdata <= {width{1'bz}};      // disconnect
   end
   always @(posedge clk)  indata <= dbus; // Reading
      
   assign #1 dbus = outdata;  // Connection to bus

   always @(posedge clk) begin  // Generate test data
      if (^dbus === 1'bX | en)
	private <= #1 private + 1;
      else
	private <= #1 private + dbus;
   end
endmodule

Ch08-Datapath/ThreeStateBus/BusUser_tb.v

`timescale 1ns/100ps

module BusUser_tb;
   parameter width = 4;  // Bit width of bus

   reg clk=1'b1,  en1, en2;
   wire [width-1:0] dbus;
   
   BusUser uut1 (.en(en1), .clk(clk), .dbus(dbus));  // Two bus users
   BusUser uut2 (.en(en2), .clk(clk), .dbus(dbus));

   initial begin
      $dumpfile("BusUser.vcd");
      $dumpvars(0,BusUser_tb);

      #1   en1 = 1'b0; en2 = 1'b0;
      #20  en1 = 1'b1;  // Bus user 1
      #100 en1 = 1'b0;
      #5   en2 = 1'b1;  // Bus user 2
      #100 en2 = 1'b0;
      #24 $finish;
   end
   
   always #10 clk = ~clk;  
endmodule

Ch08-Datapath/ThreeStateBus/BusUser.vcd
$date
	Mon Nov 30 09:46:01 2020
$end
$version
	Icarus Verilog
$end
$timescale
	100ps
$end
$scope module BusUser_tb $end
$var wire 4 ! dbus [3:0] $end
$var reg 1 " clk $end
$var reg 1 # en1 $end
$var reg 1 $ en2 $end
$scope module uut1 $end
$var wire 1 " clk $end
$var wire 4 % dbus [3:0] $end
$var wire 1 # en $end
$var reg 4 & indata [3:0] $end
$var reg 4 ' outdata [3:0] $end
$var reg 4 ( private [3:0] $end
$upscope $end
$scope module uut2 $end
$var wire 1 " clk $end
$var wire 4 ) dbus [3:0] $end
$var wire 1 $ en $end
$var reg 4 * indata [3:0] $end
$var reg 4 + outdata [3:0] $end
$var reg 4 , private [3:0] $end
$upscope $end
$upscope $end
$enddefinitions $end
#0
$dumpvars
b0 ,
bz +
bx *
bx )
b0 (
bz '
bx &
bx %
x$
x#
1"
bx !
$end
#10
b1 (
b1 ,
bz !
bz %
bz )
0$
0#
#100
0"
#200
bz *
bz &
1"
#210
b10 ,
b10 (
1#
#300
0"
#400
b10 '
1"
#410
b11 (
b11 ,
b10 !
b10 %
b10 )
#500
0"
#600
b10 *
b10 &
b11 '
1"
#610
b101 ,
b100 (
b11 !
b11 %
b11 )
#700
0"
#800
b100 '
b11 &
b11 *
1"
#810
b101 (
b1000 ,
b100 !
b100 %
b100 )
#900
0"
#1000
b100 *
b100 &
b101 '
1"
#1010
b1100 ,
b110 (
b101 !
b101 %
b101 )
#1100
0"
#1200
b110 '
b101 &
b101 *
1"
#1210
b111 (
b1 ,
b110 !
b110 %
b110 )
0#
#1260
1$
#1300
0"
#1400
b110 *
b1 +
b110 &
bz '
1"
#1410
b10 ,
b1101 (
b1 !
b1 %
b1 )
#1500
0"
#1600
b1 &
b10 +
b1 *
1"
#1610
b1110 (
b11 ,
b10 !
b10 %
b10 )
#1700
0"
#1800
b10 *
b11 +
b10 &
1"
#1810
b100 ,
b0 (
b11 !
b11 %
b11 )
#1900
0"
#2000
b11 &
b100 +
b11 *
1"
#2010
b11 (
b101 ,
b100 !
b100 %
b100 )
#2100
0"
#2200
b100 *
b101 +
b100 &
1"
#2210
b110 ,
b111 (
b101 !
b101 %
b101 )
#2260
0$
#2300
0"
#2400
b101 &
bz +
b101 *
1"
#2410
b1100 (
b1011 ,
bz !
bz %
bz )
