Ch05-RTL/Multiplier-Behaviour/Pipelined-0/multiplier-Pipelined-0-16b.v
module multiplier(a, b, y, clk);
   parameter width = 16;

   input 	        clk;
   input [width-1:0]    a, b;
   output [2*width-1:0] y;

   reg [width-1:0]      areg, breg;
   reg [2*width-1:0] 	yi;
   
   // Input registers:
   always @(posedge clk) begin
      areg <= a;
      breg <= b;
   end

   // Combinatorial part and output registers:   
   always @(posedge clk) begin
      yi <= areg *  breg;
   end

   // Output assignment:
   assign y = yi;

endmodule // multiplier

Ch05-RTL/Multiplier-Behaviour/Pipelined-0/multiplier_tb.v

module multiplier_tb;

   parameter width = 8;
   
   reg [width-1:0] a, b;
   wire [2*width-1:0] y;
   reg [2*width-1:0]  yfull;
   reg [2*width-1:0]  yprev[width-1:0];
   
   
   reg 	       clk;
   
   
   multiplier #(
		.width(width)
		) uut (
		       .a(a),
		       .b(b),
		       .y(y),
		       .clk(clk)
		       ); 

   reg [width-1:0]  xrnd = 11;
   task xorshift32;
      begin
	 xrnd = xrnd ^ (xrnd << (width*3/3)-1);
	 xrnd = xrnd ^ (xrnd >> (width/2)+1);
	 xrnd = xrnd ^ (xrnd << (width*3/4)-1);
	 xrnd = xrnd ^ (xrnd >> (width*3/3)-1);
      end endtask

   integer i,j;

   always #5 clk = ~clk;
   
   initial begin
      $dumpfile("multiplier_tb.vcd");
      // $dumpvars(1,multiplier_tb.uut.preg[0]);
      // $dumpvars(1,multiplier_tb.uut.preg[1]);
      // $dumpvars(1,multiplier_tb.uut.preg[2]);
      // $dumpvars(1,multiplier_tb.uut.preg[3]);
      // // $dumpvars(1,multiplier_tb.uut.partialsa[3]);

      // $dumpvars(1,multiplier_tb.uut.partials[0]);
      // $dumpvars(1,multiplier_tb.uut.partials[1]);
      // $dumpvars(1,multiplier_tb.uut.partials[2]);
      // $dumpvars(1,multiplier_tb.uut.partials[3]);

      // $dumpvars(1,multiplier_tb.uut.partialss[0]);
      // $dumpvars(1,multiplier_tb.uut.partialss[1]);
      // $dumpvars(1,multiplier_tb.uut.partialss[2]);    
      // $dumpvars(1,multiplier_tb.uut.partialss[3]);

      // $dumpvars(1,multiplier_tb.uut.partialsco[0]);
      // $dumpvars(1,multiplier_tb.uut.partialsco[1]);
      // $dumpvars(1,multiplier_tb.uut.partialsco[2]);
      // $dumpvars(1,multiplier_tb.uut.partialsco[3]);
      // $dumpvars(1,multiplier_tb.uut.preg[3]);
      // $dumpvars(1,multiplier_tb.uut.preg[5]);
      // $dumpvars(1,multiplier_tb.uut.preg[7]);
      $dumpvars(0, multiplier_tb);
 
      clk = 1'b0;
      
      for (i = 0; i < 20; i = i+1)
	begin
	   #2;

	   xorshift32;
	   a <= xrnd;
	   xorshift32;
	   b <= xrnd;

	   // if (i == 0) begin
	   //    a <= 4'b1101;
	   //    b <= 1;
	   // end
	   // else if (i == 1) begin
	   //    a <= 4'b1001;
	   //    b <= i;
	   // end
	   // else begin
	   //    a <= 4'b1111;
	   //    b <= i;
	   // end
	   	   
	   #1;
	   
	   yfull = a*b;
	   #7;

	   $display("%d * %d = %d (%d, Prev 0: %d)", a, b, y, yfull, yprev[0]);
	   if (y != yprev[0]) begin
	      $display("ERROR!");
	      // $finish;
	   end
	    for (j=width-1; j>0; j=j-1) begin
	      yprev[j] = yprev[j-1];
	   end
	   yprev[0] = yfull;
	   
	end // for (i = 0; i < 100; i = i+1)

      a = 8'b11111111;
      b = 8'b11111111;

      #5;
      
      $display("PASSED.");
      $finish;
      
   end

endmodule

Ch05-RTL/Multiplier-Behaviour/Pipelined-0/multiplier_tb.vcd
$date
	Sat Jul 18 18:30:17 2020
$end
$version
	Icarus Verilog
$end
$timescale
	1s
$end
$scope module multiplier_tb $end
$var wire 16 ! y [15:0] $end
$var reg 8 " a [7:0] $end
$var reg 8 # b [7:0] $end
$var reg 1 $ clk $end
$var reg 8 % xrnd [7:0] $end
$var reg 16 & yfull [15:0] $end
$var integer 32 ' i [31:0] $end
$var integer 32 ( j [31:0] $end
$scope module uut $end
$var wire 8 ) a [7:0] $end
$var wire 8 * b [7:0] $end
$var wire 1 $ clk $end
$var wire 16 + y [15:0] $end
$var reg 8 , areg [7:0] $end
$var reg 8 - breg [7:0] $end
$var reg 16 . yi [15:0] $end
$upscope $end
$scope task xorshift32 $end
$upscope $end
$upscope $end
$enddefinitions $end
#0
$dumpvars
bx .
bx -
bx ,
bx +
bx *
bx )
bx (
b0 '
bx &
b1011 %
0$
bx #
bx "
bx !
$end
#2
b11101001 #
b11101001 *
b1101111 "
b1101111 )
b11101001 %
#3
b110010100000111 &
#5
b11101001 -
b1101111 ,
1$
#10
0$
b1 '
b0 (
#12
b1001011 #
b1001011 *
b101010 "
b101010 )
b1001011 %
#13
b110001001110 &
#15
b110010100000111 !
b110010100000111 +
b110010100000111 .
b1001011 -
b101010 ,
1$
#20
0$
b10 '
b0 (
#22
b10101011 #
b10101011 *
b1101101 "
b1101101 )
b10101011 %
#23
b100100011001111 &
#25
b10101011 -
b1101101 ,
b110001001110 !
b110001001110 +
b110001001110 .
1$
#30
0$
b11 '
b0 (
#32
b1001001 #
b1001001 *
b1101010 "
b1101010 )
b1001001 %
#33
b1111000111010 &
#35
b100100011001111 !
b100100011001111 +
b100100011001111 .
b1001001 -
b1101010 ,
1$
#40
0$
b100 '
b0 (
#42
b11101011 #
b11101011 *
b101111 "
b101111 )
b11101011 %
#43
b10101100100101 &
#45
b11101011 -
b101111 ,
b1111000111010 !
b1111000111010 +
b1111000111010 .
1$
#50
0$
b101 '
b0 (
#52
b1011 #
b1011 *
b1101000 "
b1101000 )
b1011 %
#53
b10001111000 &
#55
b10101100100101 !
b10101100100101 +
b10101100100101 .
b1011 -
b1101000 ,
1$
#60
0$
b110 '
b0 (
#62
b11101001 #
b11101001 *
b1101111 "
b1101111 )
b11101001 %
#63
b110010100000111 &
#65
b11101001 -
b1101111 ,
b10001111000 !
b10001111000 +
b10001111000 .
1$
#70
0$
b111 '
b0 (
#72
b1001011 #
b1001011 *
b101010 "
b101010 )
b1001011 %
#73
b110001001110 &
#75
b110010100000111 !
b110010100000111 +
b110010100000111 .
b1001011 -
b101010 ,
1$
#80
0$
b1000 '
b0 (
#82
b10101011 #
b10101011 *
b1101101 "
b1101101 )
b10101011 %
#83
b100100011001111 &
#85
b10101011 -
b1101101 ,
b110001001110 !
b110001001110 +
b110001001110 .
1$
#90
0$
b1001 '
b0 (
#92
b1001001 #
b1001001 *
b1101010 "
b1101010 )
b1001001 %
#93
b1111000111010 &
#95
b100100011001111 !
b100100011001111 +
b100100011001111 .
b1001001 -
b1101010 ,
1$
#100
0$
b1010 '
b0 (
#102
b11101011 #
b11101011 *
b101111 "
b101111 )
b11101011 %
#103
b10101100100101 &
#105
b11101011 -
b101111 ,
b1111000111010 !
b1111000111010 +
b1111000111010 .
1$
#110
0$
b1011 '
b0 (
#112
b1011 #
b1011 *
b1101000 "
b1101000 )
b1011 %
#113
b10001111000 &
#115
b10101100100101 !
b10101100100101 +
b10101100100101 .
b1011 -
b1101000 ,
1$
#120
0$
b1100 '
b0 (
#122
b11101001 #
b11101001 *
b1101111 "
b1101111 )
b11101001 %
#123
b110010100000111 &
#125
b11101001 -
b1101111 ,
b10001111000 !
b10001111000 +
b10001111000 .
1$
#130
0$
b1101 '
b0 (
#132
b1001011 #
b1001011 *
b101010 "
b101010 )
b1001011 %
#133
b110001001110 &
#135
b110010100000111 !
b110010100000111 +
b110010100000111 .
b1001011 -
b101010 ,
1$
#140
0$
b1110 '
b0 (
#142
b10101011 #
b10101011 *
b1101101 "
b1101101 )
b10101011 %
#143
b100100011001111 &
#145
b10101011 -
b1101101 ,
b110001001110 !
b110001001110 +
b110001001110 .
1$
#150
0$
b1111 '
b0 (
#152
b1001001 #
b1001001 *
b1101010 "
b1101010 )
b1001001 %
#153
b1111000111010 &
#155
b100100011001111 !
b100100011001111 +
b100100011001111 .
b1001001 -
b1101010 ,
1$
#160
0$
b10000 '
b0 (
#162
b11101011 #
b11101011 *
b101111 "
b101111 )
b11101011 %
#163
b10101100100101 &
#165
b11101011 -
b101111 ,
b1111000111010 !
b1111000111010 +
b1111000111010 .
1$
#170
0$
b10001 '
b0 (
#172
b1011 #
b1011 *
b1101000 "
b1101000 )
b1011 %
#173
b10001111000 &
#175
b10101100100101 !
b10101100100101 +
b10101100100101 .
b1011 -
b1101000 ,
1$
#180
0$
b10010 '
b0 (
#182
b11101001 #
b11101001 *
b1101111 "
b1101111 )
b11101001 %
#183
b110010100000111 &
#185
b11101001 -
b1101111 ,
b10001111000 !
b10001111000 +
b10001111000 .
1$
#190
0$
b10011 '
b0 (
#192
b1001011 #
b1001011 *
b101010 "
b101010 )
b1001011 %
#193
b110001001110 &
#195
b110010100000111 !
b110010100000111 +
b110010100000111 .
b1001011 -
b101010 ,
1$
#200
0$
b11111111 #
b11111111 *
b11111111 "
b11111111 )
b10100 '
b0 (
#205
b11111111 -
b11111111 ,
b110001001110 !
b110001001110 +
b110001001110 .
1$
