Ch04-ModelingLatchesDelays/FlipFlops/dff-variants.v

`timescale 100ps/10ps

// DFF with no enable and no reset:
module dff (clk, d, q);
   input clk, d;
   output reg q;
   always @(posedge clk) 
     q <= #1 d;
endmodule // dff

// DFF with synchronous enable; no reset:
module dffe (clk, d, en, q);
   input clk, d, en;
   output reg q;

   always @(posedge clk)
     if (en)
       q <= #1 d;
endmodule // dffe

// DFF with synchronous enable; and asynchronous reset:
module dffer (clk, d, en, rst, q);
   input clk, d, en, rst;
   output reg q;

   always @(posedge clk or posedge rst)
     begin
	if (rst)
	  q <= #1 0;
	else if (en)
	  q <= #1 d;
     end
endmodule // dffer

// DFF with synchronous enable; and synchronous reset:
module dffesr (clk, d, en, rst, q);
   input clk, d, en, rst;
   output reg q;

   always @(posedge clk)
     begin
	if (en) begin
	   if (rst)
	     q <= #1 0;
	   else 
	     q <= #1 d;
	end
     end
endmodule // dffesr

//
// DFF Variants not in the iCE40 technology:
//

// DFF with synchronous enable; and asynchronous reset:
module dffer2 (clk, d, en, rst, q);
   input clk, d, en, rst;
   output reg q;

   always @* // (posedge clk or posedge rst)
     begin
	if (rst)
	  q <= #1 0;
	else if (en)
	  q <= #1 d;
     end
endmodule // dffer

Ch04-ModelingLatchesDelays/FlipFlops/dff-variants_tb.v

`timescale 100ps/10ps

module dffvariants_tb ();
   reg sd, sen, srst;
   reg clk = 1'b0;
   wire q, qe, qer, qesr;

   dff uut1 (.d(sd), .clk(clk), .q(q));
   dffe uut2 (.d(sd), .clk(clk), .en(sen), .q(qe));
   dffer uut3 (.d(sd), .clk(clk), .en(sen), .rst(srst), .q(qer));
   dffesr uut4 (.d(sd), .clk(clk), .en(sen), .rst(srst), .q(qesr));

   always #10 clk = ~clk;
      
   initial begin
      $dumpfile("dff-variants_tb.vcd");
      $dumpvars(0,dffvariants_tb);

      #1  sd = 1'b0; srst = 1'b1; sen = 1'b0;
            
      #2  sd = 1'b1; srst = 1'b0; sen = 1'b0;
      
      #3  sd = 1'b0; sen = 1'b1;
      #3  sd = 1'b1;
      #3  sd = 1'b0;
      #3  sd = 1'b1; sen = 1'b0;
      #3  sd = 1'b0;
      #16  sd = 1'b1;
      #3  sd = 1'b0;

      #1  srst = 1'b1; 
            
      #2  sd = 1'b1; srst = 1'b0; 
      
      #3  sd = 1'b0; sen = 1'b1;
      #3  sd = 1'b1;
      #3  sd = 1'b0;

      #10 sd = 1'b1;
      
      #20 srst = 1'b1;
      
      #20 $finish;
      
   end 
endmodule

Ch04-ModelingLatchesDelays/FlipFlops/dff-variants.vcd
$date
	Mon Sep 21 18:30:13 2020
$end
$version
	Icarus Verilog
$end
$timescale
	10ps
$end
$scope module dffvariants_tb $end
$var wire 1 ! qesr $end
$var wire 1 " qer $end
$var wire 1 # qe $end
$var wire 1 $ q $end
$var reg 1 % clk $end
$var reg 1 & sd $end
$var reg 1 ' sen $end
$var reg 1 ( srst $end
$scope module uut1 $end
$var wire 1 % clk $end
$var wire 1 & d $end
$var reg 1 $ q $end
$upscope $end
$scope module uut2 $end
$var wire 1 % clk $end
$var wire 1 & d $end
$var wire 1 ' en $end
$var reg 1 # q $end
$upscope $end
$scope module uut3 $end
$var wire 1 % clk $end
$var wire 1 & d $end
$var wire 1 ' en $end
$var wire 1 ( rst $end
$var reg 1 " q $end
$upscope $end
$scope module uut4 $end
$var wire 1 % clk $end
$var wire 1 & d $end
$var wire 1 ' en $end
$var wire 1 ( rst $end
$var reg 1 ! q $end
$upscope $end
$upscope $end
$enddefinitions $end
#0
$dumpvars
x(
x'
x&
0%
x$
x#
x"
x!
$end
#10
0'
1(
0&
#20
0"
#30
0(
1&
#60
1'
0&
#90
1&
#100
1%
#110
1$
1#
1!
1"
#120
0&
#150
0'
1&
#180
0&
#200
0%
#300
1%
#310
0$
#340
1&
#370
0&
#380
1(
#390
0"
#400
0(
1&
0%
#430
1'
0&
#460
1&
#490
0&
#500
1%
#510
0#
0!
#590
1&
#600
0%
#700
1%
#710
1!
1#
1$
1"
#790
1(
#800
0"
0%
#900
1%
#910
0!
