Ch04-ModelingLatchesDelays/FlipFlops/dff-variants.v

`timescale 100ps/10ps

// DFF with no enable and no reset:
module dff (clk, d, q);
   input clk, d;
   output reg q;
   always @(posedge clk) 
     q <= #1 d;
endmodule // dff

// DFF with synchronous enable; no reset:
module dffe (clk, d, en, q);
   input clk, d, en;
   output reg q;

   always @(posedge clk)
     if (en)
       q <= #1 d;
endmodule // dffe

// DFF with synchronous enable; and asynchronous reset:
module dffer (clk, d, en, rst, q);
   input clk, d, en, rst;
   output reg q;

   always @(posedge clk or posedge rst)
     begin
	if (rst)
	  q <= #1 0;
	else if (en)
	  q <= #1 d;
     end
endmodule // dffer

// DFF with synchronous enable; and synchronous reset:
module dffesr (clk, d, en, rst, q);
   input clk, d, en, rst;
   output reg q;

   always @(posedge clk)
     begin
	if (en) begin
	   if (rst)
	     q <= #1 0;
	   else 
	     q <= #1 d;
	end
     end
endmodule // dffesr

//
// DFF Variants not in the iCE40 technology:
//

// DFF with synchronous enable; and asynchronous reset:
module dffer2 (clk, d, en, rst, q);
   input clk, d, en, rst;
   output reg q;

   always @* // (posedge clk or posedge rst)
     begin
	if (rst)
	  q <= #1 0;
	else if (en)
	  q <= #1 d;
     end
endmodule // dffer

Ch04-ModelingLatchesDelays/FlipFlops/dff_tb.v

`timescale 100ps/10ps

module dff_tb ();
   reg s1;
   reg clk = 1'b0;
   wire s2;

   dff uut (.d(s1), .clk(clk), .q(s2));

   always #10 clk = ~clk;
      
   initial begin
      $dumpfile("dff.vcd");
      $dumpvars(0,dff_tb);

      #2  s1 = 1'b0;
      #3  s1 = 1'b1;
      #3  s1 = 1'b0;
      #3  s1 = 1'b1;
      #3  s1 = 1'b0;
      #3  s1 = 1'b1;
      #3  s1 = 1'b0;
      #3  s1 = 1'b1;
      #3  s1 = 1'b0;
      #3  s1 = 1'b1;
      #4  s1 = 1'b0;
      #3  s1 = 1'b1;
      #3  s1 = 1'b0;

      #4 $finish;
      
   end // initial begin
endmodule // rslatch_tb

Ch04-ModelingLatchesDelays/FlipFlops/dff.vcd
$date
	Mon Sep 21 10:22:55 2020
$end
$version
	Icarus Verilog
$end
$timescale
	10ps
$end
$scope module dff_tb $end
$var wire 1 ! s2 $end
$var reg 1 " clk $end
$var reg 1 # s1 $end
$scope module uut $end
$var wire 1 " clk $end
$var wire 1 # d $end
$var reg 1 ! q $end
$upscope $end
$upscope $end
$enddefinitions $end
#0
$dumpvars
x#
0"
x!
$end
#20
0#
#50
1#
#80
0#
#100
1"
#110
0!
1#
#140
0#
#170
1#
#200
0#
0"
#230
1#
#260
0#
#290
1#
#300
1"
#310
1!
#330
0#
#360
1#
#390
0#
