Ch05-RTL/Multiplier-CarrySave/Pipelined-h/multiplier-Pipelined-h-32b.v
module multiplier(a, b, y, clk);

   parameter width = 32;
   input [width-1:0] a, b;
   output [2*width-1:0] y;
      // output  y;
   input 	      clk;

   reg [width-1:0]    areg, breg;
   wire [width-1:0]    partialsa [width-1:0];
   wire [width-1:0]    partialsb [width-1:0];
   wire [width-1:0]    partialss [width-1:0];
   wire [width-1:0]    partialsci [width-1:0];
   wire [width-1:0]    partialsco [width-1:0];

   reg [2*width-1:0]  psreg;  // input register for the secnd pipeline stage
   reg [width-1:0]    pcreg;  // input register for the secnd pipeline stage
   
   reg [width-1:0]    lrowco;
   
   reg [2*width-1:0]  yi, yreg;
   
   // genvar 		  i;
   // assign partials[width-1 : 0] = a[0] ? b : 0;
   // generate for (i = 1; i < width; i = i+1) begin:gen
   //    assign partials[width*(i+1)-1 : width*i] = (a[i] ? b << i : 0) +
   // 						 partials[width*i-1 : width*(i-1)];
   // end endgenerate

   // assign y = partials[width*width-1 : width*(width-1)];

   integer 	      i;
   genvar 	      j;
   
   // Input registers:
   always @(posedge clk) begin
      areg <= a;
      breg <= b;
   end

  // First pipeline stage:
   assign partialsa[0] = 0;
   assign partialsb[0] = areg[0] ? breg : 0;
   assign partialsci[0] = 0;

   assign partialss[0] = partialsa[0] ^ partialsb[0] ^ partialsci[0];
   assign partialsco[0] = (partialsa[0] & partialsb[0]) 
     | (partialsa[0] & partialsci[0])
       | (partialsb[0] & partialsci[0]);
      
   generate for (j = 1; j < width; j = j+1) begin
      assign partialsa[j]  = partialss[j-1] >> 1;
      assign partialsb[j]  = areg[j] ? (breg): 0;
      assign partialsci[j] = partialsco[j-1];
	 	 
      assign partialss[j] = partialsa[j] ^ partialsb[j] ^ partialsci[j];
      assign partialsco[j] = (partialsa[j] & partialsb[j]) 
	| (partialsa[j] & partialsci[j])
	  | (partialsb[j] & partialsci[j]);
   end endgenerate

   // Input registers for the second pipeline stage:
   always @(posedge clk) begin
      for (i = 0; i < width-1; i=i+1) begin
	 psreg[i] <= partialss[i][0];
      end
      psreg[2*width-2:width-1] <= partialss[width-1];

      pcreg <= partialsco[width-1];
   end
         
   // Second pipeline stage:
   always @(posedge clk) begin
      for (i = 0; i < width; i = i+1) begin
	 // yi[i] = partialss[i][0];
	 yi[i] = psreg[i];
      end
      // Last summation row:
      // yi[width] = partialsco[width-1][0] ^ partialss[width-1][1];
      // lrowco[0] = partialsco[width-1][0] & partialss[width-1][1];
      yi[width] = pcreg[0] ^ psreg[width];
      lrowco[0] = pcreg[0] & psreg[width];
      
      for (i = 1; i < width-1; i = i+1) begin
	 // yi[i+width] = partialsco[width-1][i] ^ partialss[width-1][i+1] ^ lrowco[i-1];
	 // lrowco[i] = (partialsco[width-1][i] & partialss[width-1][i+1])
	 //   | (partialsco[width-1][i] & lrowco[i-1])
	 //     |  (partialss[width-1][i+1] & lrowco[i-1]);
	 yi[i+width] = pcreg[i] ^ psreg[width+i] ^ lrowco[i-1];
	 lrowco[i] = (pcreg[i] & psreg[width+i])
	   | (pcreg[i] & lrowco[i-1])
	     |  (psreg[width+i] & lrowco[i-1]);
	 end

      // yi[2*width-1] = partialsco[width-1][width-1] ^ lrowco[width-2];
      // lrowco[width-1] = partialsco[width-1][width-1] & lrowco[width-2];
      yi[2*width-1] = pcreg[width-1] ^ lrowco[width-2];
      lrowco[width-1] = pcreg[width-1] & lrowco[width-2];
      
   end // always @ (posedge clk)

   assign #1 y = yi;
         
endmodule // multiplier

Ch05-RTL/Multiplier-CarrySave/Pipelined-h/multiplier_tb.v

module multiplier_tb;

   parameter width = 32;
   
   reg [width-1:0] a, b;
   wire [2*width-1:0] y;
   reg [2*width-1:0]  yfull;
   reg [2*width-1:0]  yprev[width-1:0];
 
   
   reg 	       clk;
   
   
   multiplier #(
		.width(width)
		) uut (
		       .a(a),
		       .b(b),
		       .y(y),
		       .clk(clk)
		       ); 

   reg [width-1:0]  xrnd = 9;
   task xorshift32;
      begin
	 xrnd = xrnd ^ (xrnd << (width*3/12)-1);
	 xrnd = xrnd ^ (xrnd >> (width/2)+1);
	 xrnd = xrnd ^ (xrnd << (width*3/4)-1);
	 xrnd = xrnd ^ (xrnd >> (width*3/12)-1);
      end endtask

   integer i, j;

   always #5 clk = ~clk;
   
   initial begin
      $dumpfile("multiplier_tb.vcd");
      $dumpvars(1,multiplier_tb.uut.partialsa[0]);
      $dumpvars(1,multiplier_tb.uut.partialsa[1]);
      $dumpvars(1,multiplier_tb.uut.partialsa[2]);
      $dumpvars(1,multiplier_tb.uut.partialsa[3]);

      $dumpvars(1,multiplier_tb.uut.partialsb[0]);
      $dumpvars(1,multiplier_tb.uut.partialsb[1]);
      $dumpvars(1,multiplier_tb.uut.partialsb[2]);
      $dumpvars(1,multiplier_tb.uut.partialsb[3]);

      $dumpvars(1,multiplier_tb.uut.partialss[0]);
      $dumpvars(1,multiplier_tb.uut.partialss[1]);
      $dumpvars(1,multiplier_tb.uut.partialss[2]);    
      $dumpvars(1,multiplier_tb.uut.partialss[3]);

      $dumpvars(1,multiplier_tb.uut.partialsco[0]);
      $dumpvars(1,multiplier_tb.uut.partialsco[1]);
      $dumpvars(1,multiplier_tb.uut.partialsco[2]);
      $dumpvars(1,multiplier_tb.uut.partialsco[3]);
      // $dumpvars(1,multiplier_tb.uut.preg[3]);
      // $dumpvars(1,multiplier_tb.uut.preg[5]);
      // $dumpvars(1,multiplier_tb.uut.preg[7]);
      $dumpvars(0, multiplier_tb);
 
      clk = 1'b0;
      
      for (i = 0; i < 100; i = i+1)
	begin
	   #1;

	   xorshift32;
	   a <= xrnd;
	   xorshift32;
	   b <= xrnd;

	   #1;
	   
	   yfull = a*b;
	   #8;

	   $display("%d * %d = %d (%d, Prev 1: %d)", a, b, y, yfull, yprev[1]);
	   if (y != yprev[1]) begin
	      $display("ERROR!");
	      // $finish;
	   end
	    for (j=width-1; j>0; j=j-1) begin
	      yprev[j] = yprev[j-1];
	   end
	   yprev[0] = yfull;

	end // for (i = 0; i < 100; i = i+1)

      a = 8'b11111111;
      b = 8'b11111111;

      #5;
      
      $display("PASSED.");
      $finish;
      
   end

endmodule

Ch05-RTL/Multiplier-CarrySave/Pipelined-h/multiplier_tb.vcd
$date
	Fri Jul 17 16:16:44 2020
$end
$version
	Icarus Verilog
$end
$timescale
	1s
$end
$scope module multiplier_tb $end
$scope module uut $end
$var wire 32 ! \partialsa[0] [31:0] $end
$upscope $end
$upscope $end
$scope module multiplier_tb $end
$scope module uut $end
$var wire 32 " \partialsa[1] [31:0] $end
$upscope $end
$upscope $end
$scope module multiplier_tb $end
$scope module uut $end
$var wire 32 # \partialsa[2] [31:0] $end
$upscope $end
$upscope $end
$scope module multiplier_tb $end
$scope module uut $end
$var wire 32 $ \partialsa[3] [31:0] $end
$upscope $end
$upscope $end
$scope module multiplier_tb $end
$scope module uut $end
$var wire 32 % \partialsb[0] [31:0] $end
$upscope $end
$upscope $end
$scope module multiplier_tb $end
$scope module uut $end
$var wire 32 & \partialsb[1] [31:0] $end
$upscope $end
$upscope $end
$scope module multiplier_tb $end
$scope module uut $end
$var wire 32 ' \partialsb[2] [31:0] $end
$upscope $end
$upscope $end
$scope module multiplier_tb $end
$scope module uut $end
$var wire 32 ( \partialsb[3] [31:0] $end
$upscope $end
$upscope $end
$scope module multiplier_tb $end
$scope module uut $end
$var wire 32 ) \partialss[0] [31:0] $end
$upscope $end
$upscope $end
$scope module multiplier_tb $end
$scope module uut $end
$var wire 32 * \partialss[1] [31:0] $end
$upscope $end
$upscope $end
$scope module multiplier_tb $end
$scope module uut $end
$var wire 32 + \partialss[2] [31:0] $end
$upscope $end
$upscope $end
$scope module multiplier_tb $end
$scope module uut $end
$var wire 32 , \partialss[3] [31:0] $end
$upscope $end
$upscope $end
$scope module multiplier_tb $end
$scope module uut $end
$var wire 32 - \partialsco[0] [31:0] $end
$upscope $end
$upscope $end
$scope module multiplier_tb $end
$scope module uut $end
$var wire 32 . \partialsco[1] [31:0] $end
$upscope $end
$upscope $end
$scope module multiplier_tb $end
$scope module uut $end
$var wire 32 / \partialsco[2] [31:0] $end
$upscope $end
$upscope $end
$scope module multiplier_tb $end
$scope module uut $end
$var wire 32 0 \partialsco[3] [31:0] $end
$upscope $end
$upscope $end
$scope module multiplier_tb $end
$var wire 64 1 y [63:0] $end
$var reg 32 2 a [31:0] $end
$var reg 32 3 b [31:0] $end
$var reg 1 4 clk $end
$var reg 32 5 xrnd [31:0] $end
$var reg 64 6 yfull [63:0] $end
$var integer 32 7 i [31:0] $end
$var integer 32 8 j [31:0] $end
$scope module uut $end
$var wire 32 9 a [31:0] $end
$var wire 32 : b [31:0] $end
$var wire 1 4 clk $end
$var wire 64 ; y [63:0] $end
$var reg 32 < areg [31:0] $end
$var reg 32 = breg [31:0] $end
$var reg 32 > lrowco [31:0] $end
$var reg 32 ? pcreg [31:0] $end
$var reg 64 @ psreg [63:0] $end
$var reg 64 A yi [63:0] $end
$var integer 32 B i [31:0] $end
$scope begin genblk1[1] $end
$upscope $end
$scope begin genblk1[2] $end
$upscope $end
$scope begin genblk1[3] $end
$upscope $end
$scope begin genblk1[4] $end
$upscope $end
$scope begin genblk1[5] $end
$upscope $end
$scope begin genblk1[6] $end
$upscope $end
$scope begin genblk1[7] $end
$upscope $end
$scope begin genblk1[8] $end
$upscope $end
$scope begin genblk1[9] $end
$upscope $end
$scope begin genblk1[10] $end
$upscope $end
$scope begin genblk1[11] $end
$upscope $end
$scope begin genblk1[12] $end
$upscope $end
$scope begin genblk1[13] $end
$upscope $end
$scope begin genblk1[14] $end
$upscope $end
$scope begin genblk1[15] $end
$upscope $end
$scope begin genblk1[16] $end
$upscope $end
$scope begin genblk1[17] $end
$upscope $end
$scope begin genblk1[18] $end
$upscope $end
$scope begin genblk1[19] $end
$upscope $end
$scope begin genblk1[20] $end
$upscope $end
$scope begin genblk1[21] $end
$upscope $end
$scope begin genblk1[22] $end
$upscope $end
$scope begin genblk1[23] $end
$upscope $end
$scope begin genblk1[24] $end
$upscope $end
$scope begin genblk1[25] $end
$upscope $end
$scope begin genblk1[26] $end
$upscope $end
$scope begin genblk1[27] $end
$upscope $end
$scope begin genblk1[28] $end
$upscope $end
$scope begin genblk1[29] $end
$upscope $end
$scope begin genblk1[30] $end
$upscope $end
$scope begin genblk1[31] $end
$upscope $end
$upscope $end
$scope task xorshift32 $end
$upscope $end
$upscope $end
$enddefinitions $end
#0
$dumpvars
bx B
bx A
bx @
bx ?
bx >
bx =
bx <
bx ;
bx :
bx 9
bx 8
b0 7
bx 6
b1001 5
04
bx 3
bx 2
bx 1
b0xxxxxxxxxxxxxxxxxxxxxxxxxxxxxxx 0
b0xxxxxxxxxxxxxxxxxxxxxxxxxxxxxxx /
b0xxxxxxxxxxxxxxxxxxxxxxxxxxxxxxx .
b0 -
bx ,
bx +
bx *
bx )
bx (
bx '
bx &
bx %
b0xxxxxxxxxxxxxxxxxxxxxxxxxxxxxxx $
b0xxxxxxxxxxxxxxxxxxxxxxxxxxxxxxx #
b0xxxxxxxxxxxxxxxxxxxxxxxxxxxxxxx "
b0 !
$end
#1
b100010010011110111001000001100 3
b100010010011110111001000001100 :
b1000100000010010000010010000000 2
b1000100000010010000010010000000 9
b100010010011110111001000001100 5
#2
b100100011110010011111011000010010111111011010011011000000000 6
#5
b0 /
b0 0
b0 "
b0 .
b0 #
b0 $
b0 )
b0 *
b0 +
b0 ,
b0 %
b0 &
b0 '
b0 (
b100010010011110111001000001100 =
b1000100000010010000010010000000 <
b0xxxxxxxxxxxxxxxxxxxxxxxxxxxxxxx ?
b11111 B
14
#10
04
b1 7
b0 8
#11
b1000111110010010000010111101100 3
b1000111110010010000010111101100 :
b1111110100010101001101000011010 2
b1111110100010101001101000011010 9
b1000111110010010000010111101100 5
#12
b10001101111011110011100111110110010001001100101001000111111000 6
#15
b1110000000000000101101000 0
b10001111100100100000101111011 $
b100011111001001000001011110110 +
b100011111001001000001011110110 #
b1000111110010010000010111101100 *
b1010110001110110100010010010111 ,
b1000111110010010000010111101100 &
b1000111110010010000010111101100 (
b10100000000000100 ?
bx000100100011101000011111010110010010111111011010011011000000000 @
b1000111110010010000010111101100 =
b1111110100010101001101000011010 <
b0xxxxxxxxxxxxxxxxxxxxxxxxxxxxxxx >
b11111 B
14
#20
04
b10 7
b0 8
#21
b10101111101010111110001100001 3
b10101111101010111110001100001 :
b10000110110001000011010100001101 2
b10000110110001000011010100001101 9
b10101111101010111110001100001 5
#22
b101110001111010100111001101011110000011110110110010111101101 6
#25
b101011101010101110000000000 /
b1000010001000001000110111100 $
b1010111110101011111000110000 "
b101011111010101111100011000 #
b101011101010101110000100000 0
b10000100010000010001101111001 +
b10101111101010111110001100001 )
b1010111110101011111000110000 *
b11000110001000011000111011101 ,
b10101111101010111110001100001 '
b10101111101010111110001100001 %
b0 &
b10101111101010111110001100001 (
b10101111101010111110001100001 =
b10000110110001000011010100001101 <
b111000010000000010100001100 ?
bx001110001110011110010010111000110010001001100101001000111111000 @
b10000000000001100 >
b100100011110010011111011000010010111111011010011011000000000 A
b11111 B
14
#26
b100100011110010011111011000010010111111011010011011000000000 1
b100100011110010011111011000010010111111011010011011000000000 ;
#30
04
b11 7
b0 8
#31
b11111100011111000110100001111100 3
b11111100011111000110100001111100 :
b1001101110100011010110100110010 2
b1001101110100011010110100110010 9
b11111100011111000110100001111100 5
#32
b100110011000000001101111100111111111100001001000011010000111000 6
#35
b0 .
b1111110001111100011010000111110 #
b0 "
b0 /
b111111000111110001101000011111 $
b11111100011111000110100001111100 *
b0 )
b1111110001111100011010000111110 +
b0 0
b111111000111110001101000011111 ,
b11111100011111000110100001111100 &
b0 %
b0 '
b0 (
b1001000010010100001000000 ?
bx000101001101110001010110101101011110000011110110110010111101101 @
b11111100011111000110100001111100 =
b1001101110100011010110100110010 <
b11100000000000000000100000000 >
b10001101111011110011100111110110010001001100101001000111111000 A
b11111 B
14
#36
b10001101111011110011100111110110010001001100101001000111111000 1
b10001101111011110011100111110110010001001100101001000111111000 ;
#40
04
b100 7
b0 8
#41
b1110010110111010000000001001 3
b1110010110111010000000001001 :
b1101110100101001010011100110110 2
b1101110100101001010011100110110 9
b1110010110111010000000001001 5
#42
b11000110011101101010001110100101111111011011010000011100110 6
#45
b100000010010000000000000000 0
b10101100101011100000000110 ,
b110000010011000000000000000 /
b100101110110011100000000110 $
b111001011011101000000000100 #
b1001011101100111000000001101 +
b1110010110111010000000001001 *
b1110010110111010000000001001 '
b1110010110111010000000001001 &
b1110010110111010000000001001 =
b1101110100101001010011100110110 <
b100100000001000000000000100000 ?
bx010100010111100001101111010111111111100001001000011010000111000 @
b11000000010100001000000 >
b101110001111010100111001101011110000011110110110010111101101 A
b11111 B
14
#46
b101110001111010100111001101011110000011110110110010111101101 1
b101110001111010100111001101011110000011110110110010111101101 ;
#50
04
b101 7
b0 8
#51
b1100011000101100111000011101000 3
b1100011000101100111000011101000 :
b10000100100000001010001000100110 2
b10000100100000001010001000100110 9
b1100011000101100111000011101000 5
#52
b11001101001001010111000011001011111100110001111001001001110000 6
#55
b100001000000100010000001000000 0
b1000010011001001010000101110 ,
b110001100010110011100001110100 #
b100001000000100011000001100000 /
b101001010011101010010001001110 $
b1100011000101100111000011101000 *
b1010010100111010100100010011100 +
b1100011000101100111000011101000 &
b1100011000101100111000011101000 '
b110000010001000000000000001 ?
bx000000000101011001101010001110000101111111011011010000011100110 @
b1100011000101100111000011101000 =
b10000100100000001010001000100110 <
b100000001111000000000000100000 >
b100110011000000001101111100111111111100001001000011010000111000 A
b11111 B
14
#56
b100110011000000001101111100111111111100001001000011010000111000 1
b100110011000000001101111100111111111100001001000011010000111000 ;
#60
04
b110 7
b0 8
#61
b11011101001011100110011010000101 3
b11011101001011100110011010000101 :
b10010110100000010010110000011110 2
b10010110100000010010110000011110 9
b11011101001011100110011010000101 5
#62
b1000001000001000110010101001000101111100000100111101111110010110 6
#65
b1101110100101110011001101000010 #
b1001100000001100010001000000000 /
b1011001110111001010101011100011 $
b1011101000011100010001010000001 0
b11001000111101001110111001100110 ,
b11011101001011100110011010000101 *
b10110011101110010101010111000111 +
b11011101001011100110011010000101 (
b11011101001011100110011010000101 &
b11011101001011100110011010000101 '
b11011101001011100110011010000101 =
b10010110100000010010110000011110 <
b11000101000100000001101000 ?
bx011000000110101000110111100101011111100110001111001001001110000 @
b10000000000000000000 >
b11000110011101101010001110100101111111011011010000011100110 A
b11111 B
14
#66
b11000110011101101010001110100101111111011011010000011100110 1
b11000110011101101010001110100101111111011011010000011100110 ;
#70
04
b111 7
b0 8
#71
b11001101100001111110011110110110 3
b11001101100001111110011110110110 :
b11001110000000100011101100001001 2
b11001110000000100011101100001001 9
b11001101100001111110011110110110 5
#72
b1010010101100101001001101110100111001111100110100001011101100110 6
#75
b1100110110000111111001111011011 "
b110011011000011111100111101101 #
b0 /
b11001101100001111110011110110 $
b1001100000001110010010110110 0
b11001101100001111110011110110110 )
b1100110110000111111001111011011 *
b110011011000011111100111101101 +
b11010100001101110001101101000000 ,
b11001101100001111110011110110110 %
b0 &
b0 '
b11001101100001111110011110110110 (
b100001000100010011010000101 ?
bx111110111100110101001000000110001111100000100111101111110010110 @
b11001101100001111110011110110110 =
b11001110000000100011101100001001 <
b1101000000001111001000 >
b11001101001001010111000011001011111100110001111001001001110000 A
b11111 B
14
#76
b11001101001001010111000011001011111100110001111001001001110000 1
b11001101001001010111000011001011111100110001111001001001110000 ;
#80
04
b1000 7
b0 8
#81
b11100100110001110010100111011010 3
b11100100110001110010100111011010 :
b11001001111001001101001111111011 2
b11001001111001001101001111111011 9
b11100100110001110010100111011010 5
#82
b1011010001101100110111101010110111100110111011001011011010111110 6
#85
b1000000010000100000000010001000 /
b10101100010001010111100101001 $
b101011000100010101111001010011 +
b1100000010000110000000011001000 .
b1001011010100100101111010011011 #
b1110010011000111001010011101101 "
b1000100110000100010100110001000 0
b10010110101001001011110100110111 *
b11100100110001110010100111011010 )
b10110001000011011000011001111011 ,
b11100100110001110010100111011010 &
b11100100110001110010100111011010 %
b11100100110001110010100111011010 (
b11100100110001110010100111011010 =
b11001001111001001101001111111011 <
b1001100100001011110001110110100 ?
bx101100011011111010000110011010111001111100110100001011101100110 @
b1111101111001100010010000001100 >
b1000001000001000110010101001000101111100000100111101111110010110 A
b11111 B
14
#86
b1000001000001000110010101001000101111100000100111101111110010110 1
b1000001000001000110010101001000101111100000100111101111110010110 ;
#90
04
b1001 7
b0 8
#91
b1111000010011110101011001110110 3
b1111000010011110101011001110110 :
b111110101011100010000001111101 2
b111110101011100010000001111101 9
b1111000010011110101011001110110 5
#92
b1110101110101000011000010001000000001101111111111011110011110 6
#95
b110011001011100100000111110101 $
b111100001001111010101100111011 "
b0 .
b11110000100111101010110011101 #
b11000000000110101010000010100 /
b1100110010111001000001111101011 +
b1111000010011110101011001110110 )
b111100001001111010101100111011 *
b111000000011110101010001110100 0
b1010011011000100100001110010111 ,
b1111000010011110101011001110110 '
b1111000010011110101011001110110 %
b0 &
b1111000010011110101011001110110 (
b1100000110001010010100101011000 ?
bx101001110100111101101010101010111100110111011001011011010111110 @
b1111000010011110101011001110110 =
b111110101011100010000001111101 <
b1011000100111111100001100110100 >
b1010010101100101001001101110100111001111100110100001011101100110 A
b11111 B
14
#96
b1010010101100101001001101110100111001111100110100001011101100110 1
b1010010101100101001001101110100111001111100110100001011101100110 ;
#100
04
b1010 7
b0 8
#101
b110100011100101100011001101011 3
b110100011100101100011001101011 :
b11101110111111000101000000001 2
b11101110111111000101000000001 9
b110100011100101100011001101011 5
#102
b11000011110110011001011101100001001100111010111010001101011 6
#105
b1101000111001011000110011010 #
b11010001110010110001100110101 *
b11010001110010110001100110101 "
b0 /
b110100011100101100011001101 $
b110100011100101100011001101011 )
b1101000111001011000110011010 +
b0 0
b110100011100101100011001101 ,
b110100011100101100011001101011 %
b0 '
b0 (
b110100011100101100011001101011 =
b11101110111111000101000000001 <
b1000100001000010010 ?
bx001110101110000110010100001000000000001101111111111011110011110 @
b1000011100001110010000101010000 >
b1011010001101100110111101010110111100110111011001011011010111110 A
b11111 B
14
#106
b1011010001101100110111101010110111100110111011001011011010111110 1
b1011010001101100110111101010110111100110111011001011011010111110 ;
#110
04
b1011 7
b0 8
#111
b101101110110001011000110100101 3
b101101110110001011000110100101 :
b10111101111010001101011010001001 2
b10111101111010001101011010001001 9
b101101110110001011000110100101 5
#112
b10001000000010101011011111001101111011111111101111111101001101 6
#115
b101101110110001011000110100 $
b1011011101100010110001101001 +
b1011011101100010110001101001 #
b10110111011000101100011010010 *
b101100110000001000000100100 0
b10110111011000101100011010010 "
b101000011000111010011110010001 ,
b101101110110001011000110100101 )
b101101110110001011000110100101 (
b101101110110001011000110100101 %
b10000000001 ?
bx000011000011110110010001011101000001001100111010111010001101011 @
b101101110110001011000110100101 =
b10111101111010001101011010001001 <
b1100001000010000 >
b1110101110101000011000010001000000001101111111111011110011110 A
b11111 B
14
#116
b1110101110101000011000010001000000001101111111111011110011110 1
b1110101110101000011000010001000000001101111111111011110011110 ;
#120
04
b1100 7
b0 8
#121
b11101001001101100111110110110100 3
b11101001001101100111110110110100 :
b110011011001100000001111100010 2
b110011011001100000001111100010 9
b11101001001101100111110110110100 5
#122
b10111011010010110010100100101001110111010011000001010011101000 6
#125
b0 /
b111010010011011001111101101101 $
b1110100100110110011111011011010 +
b0 .
b1110100100110110011111011011010 #
b0 "
b0 0
b11101001001101100111110110110100 *
b0 )
b111010010011011001111101101101 ,
b11101001001101100111110110110100 &
b0 %
b0 (
b11101001001101100111110110110100 =
b110011011001100000001111100010 <
b1101100010001010000110100101 ?
bx001010001111010000011000100111001111011111111101111111101001101 @
b0 >
b11000011110110011001011101100001001100111010111010001101011 A
b11111 B
14
#126
b11000011110110011001011101100001001100111010111010001101011 1
b11000011110110011001011101100001001100111010111010001101011 ;
#130
04
b1101 7
b0 8
#131
b10000101000100110111110110010110 3
b10000101000100110111110110010110 :
b101010010111001000111110001101 2
b101010010111001000111110001101 9
b10000101000100110111110110010110 5
#132
b1011000000101010100000011101011101100110010101111010110011110 6
#135
b1000000000101110100000100 /
b1010010001010111101000101111001 $
b1000000110101110100010100 0
b1000010100010011011111011001011 "
b100001010001001101111101100101 #
b10100100010101111010001011110011 +
b11010110001110001111000111101011 ,
b10000101000100110111110110010110 )
b1000010100010011011111011001011 *
b10000101000100110111110110010110 '
b10000101000100110111110110010110 (
b10000101000100110111110110010110 %
b0 &
b100000010100100000000 ?
bx010111011000010101000010100101001110111010011000001010011101000 @
b10000101000100110111110110010110 =
b101010010111001000111110001101 <
b11101111110000000000000001100 >
b10001000000010101011011111001101111011111111101111111101001101 A
b11111 B
14
#136
b10001000000010101011011111001101111011111111101111111101001101 1
b10001000000010101011011111001101111011111111101111111101001101 ;
#140
04
b1110 7
b0 8
#141
b1000110000011000001001000000001 3
b1000110000011000001001000000001 :
b1101100011101001110101110100001 2
b1101100011101001110101110100001 9
b1000110000011000001001000000001 5
#142
b1110110101101000101011000100110110110100100100011110110100001 6
#145
b10001100000110000010010000000 #
b100011000001100000100100000000 *
b100011000001100000100100000000 "
b0 /
b1000110000011000001001000000 $
b1000110000011000001001000000001 )
b10001100000110000010010000000 +
b0 0
b1000110000011000001001000000 ,
b1000110000011000001001000000001 %
b0 '
b0 (
b1000110000011000001001000000001 =
b1101100011101001110101110100001 <
b1000000000100000100000000 ?
bx001010100000101000011110011101011101100110010101111010110011110 @
b10000100000000 >
b10111011010010110010100100101001110111010011000001010011101000 A
b11111 B
14
#146
b10111011010010110010100100101001110111010011000001010011101000 1
b10111011010010110010100100101001110111010011000001010011101000 ;
#150
04
b1111 7
b0 8
#151
b10010110001101000001111011111110 3
b10010110001101000001111011111110 :
b1100001100011100011100110 2
b1100001100011100011100110 9
b10010110001101000001111011111110 5
#152
b11100100111101001100100110010000100011110110100000110100 6
#155
b10000100000000100001000000 0
b1101100100001110000011010111110 ,
b0 .
b1001011000110100000111101111111 #
b10000100000000111001111110 /
b1101110100101110000100011000000 $
b0 "
b10010110001101000001111011111110 *
b11011101001011100001000110000001 +
b0 )
b10010110001101000001111011111110 &
b10010110001101000001111011111110 '
b0 %
b100000011000001000000000000 ?
bx001100110100001000001011000100110110110100100100011110110100001 @
b10010110001101000001111011111110 =
b1100001100011100011100110 <
b1000000000000111100000000 >
b1011000000101010100000011101011101100110010101111010110011110 A
b11111 B
14
#156
b1011000000101010100000011101011101100110010101111010110011110 1
b1011000000101010100000011101011101100110010101111010110011110 ;
#160
04
b10000 7
b0 8
#161
b1010001110010100011100011001010 3
b1010001110010100011100011001010 :
b1111101010000000101000110101100 2
b1111101010000000101000110101100 9
b1010001110010100011100011001010 5
#162
b10100000000100010010100110000011000100010101100001000110111000 6
#165
b0 #
b0 /
b101000111001010001110001100101 $
b110000000001100001000000 0
b1111001001011110010010010101111 ,
b0 *
b1010001110010100011100011001010 +
b1010001110010100011100011001010 (
b0 &
b1010001110010100011100011001010 '
b1010001110010100011100011001010 =
b1111101010000000101000110101100 <
b0 ?
bx000000011100100111101001100100110010000100011110110100000110100 @
b0 >
b1110110101101000101011000100110110110100100100011110110100001 A
b11111 B
14
#166
b1110110101101000101011000100110110110100100100011110110100001 1
b1110110101101000101011000100110110110100100100011110110100001 ;
#170
04
b10001 7
b0 8
#171
b10001111010101111111111110011001 3
b10001111010101111111111110011001 :
b1100100100111101010101110101110 2
b1100100100111101010101110101110 9
b10001111010101111111111110011001 5
#172
b11100001010111001110000100100010111001111110001110110011111110 6
#175
b111000000111111111110001000 /
b1000111101010111111111111001100 #
b1100100011111100000000000101010 $
b111010101111111111110001000 0
b10001111010101111111111110011001 *
b11001000111111000000000001010101 +
b11101100001010100000000000111011 ,
b10001111010101111111111110011001 &
b10001111010101111111111110011001 '
b10001111010101111111111110011001 (
b10000000010100001100011000010 ?
bx001011111111010001100011001111011000100010101100001000110111000 @
b10001111010101111111111110011001 =
b1100100100111101010101110101110 <
b11100100111101001100100110010000100011110110100000110100 A
b11111 B
14
#176
b11100100111101001100100110010000100011110110100000110100 1
b11100100111101001100100110010000100011110110100000110100 ;
#180
04
b10010 7
b0 8
#181
b10111101110111101010111111101 3
b10111101110111101010111111101 :
b10000011001011000111000100001111 2
b10000011001011000111000100001111 9
b10111101110111101010111111101 5
#182
b110000101001001111010100010010001011111100100011011011010011 6
#185
b11100110011100000011111100 .
b1011110111011110101011111110 "
b1110001100110001111110000001 #
b111101110111101010111111101 /
b1101000010001000010101000000 $
b10111101110111101010111111101 )
b11100011001100011111100000011 *
b11010000100010000101010000000 +
b111101110111101010111111101 0
b11101000010001000010101000000 ,
b10111101110111101010111111101 %
b10111101110111101010111111101 &
b10111101110111101010111111101 '
b10111101110111101010111111101 (
b10111101110111101010111111101 =
b10000011001011000111000100001111 <
b1010100101011000100011000 ?
bx011011100000100100001110011000010111001111110001110110011111110 @
b10111111110100011000110011110 >
b10100000000100010010100110000011000100010101100001000110111000 A
b11111 B
14
#186
b10100000000100010010100110000011000100010101100001000110111000 1
b10100000000100010010100110000011000100010101100001000110111000 ;
#190
04
b10011 7
b0 8
#191
b10100010011100111000110000011 3
b10100010011100111000110000011 :
b11100001000100001110110011001001 2
b11100001000100001110110011001001 9
b10100010011100111000110000011 5
#192
b1000111011010010010010111001101111101011010111110001111011011 6
#195
b1010001001110011100011000001 "
b0 .
b101000100111001110001100000 #
b10100010011100111000110000 $
b10100010011100111000110000011 )
b1010001001110011100011000001 *
b0 /
b101000100111001110001100000 +
b10000100000000000000 0
b10110110001111011111110110011 ,
b10100010011100111000110000011 %
b0 &
b0 '
b10100010011100111000110000011 (
b100100101000010010001100 ?
bx000101110010110101110001011100010001011111100100011011011010011 @
b10100010011100111000110000011 =
b11100001000100001110110011001001 <
b111000000001000011100110000 >
b11100001010111001110000100100010111001111110001110110011111110 A
b11111 B
14
#196
b11100001010111001110000100100010111001111110001110110011111110 1
b11100001010111001110000100100010111001111110001110110011111110 ;
#200
04
b10100 7
b0 8
#201
b10101100110100010111100011110110 3
b10101100110100010111100011110110 :
b11101110101010000100010011101011 2
b11101110101010000100010011101011 9
b10101100110100010111100011110110 5
#202
b1010000100011100010101100111001001011101110110110110000111010010 6
#205
b100010000000010000001000010 /
b111100100011100110110100011010 $
b1111001000111001101101000110100 +
b100010000000011100001110010 .
b1111101010111001110001001000110 #
b1010110011010001011110001111011 "
b101100110000000110100001010010 0
b11111010101110011100010010001101 *
b10101100110100010111100011110110 )
b10010100000111110011010110101110 ,
b10101100110100010111100011110110 &
b10101100110100010111100011110110 %
b10101100110100010111100011110110 (
b10101100110100010111100011110110 =
b11101110101010000100010011101011 <
b100010011000111000100000011 ?
bx000110110001101110110000111000001111101011010111110001111011011 @
b11100101101000000010111000 >
b110000101001001111010100010010001011111100100011011011010011 A
b11111 B
14
#206
b110000101001001111010100010010001011111100100011011011010011 1
b110000101001001111010100010010001011111100100011011011010011 ;
#210
04
b10101 7
b0 8
#211
b11001000111010101101000110111100 3
b11001000111010101101000110111100 :
b100100001001011011101100000011 2
b100100001001011011101100000011 9
b11001000111010101101000110111100 5
#212
b1110001011110101000100011010010100010001000001100100100110100 6
