Ch05-RTL/PipelinePattern/pipeline.v
module pipeline (reset,clock,in,out);
   input reset, clock;
   input [3:0] in;
   output reg [3:0] out;

   reg 	 [3:0]  in_pipe;
   
   always @(posedge clock or posedge reset)
     begin
	if(reset)
	  out <= 0;
	else // Pipeline stage processing
	  out <= in_pipe; 
     end

   always @(posedge clock or posedge reset)
     begin
	if(reset)
	  in_pipe <= 0;
	else
	  in_pipe <= in;
     end
endmodule

Ch05-RTL/PipelinePattern/pipeline_tb.v
module pipeline_tb;
   
   reg reset, clk;

   reg [3:0] in;
   wire [3:0]  out;

   pipeline uut (
		 .reset(reset),
		 .in(in),
		 .clock(clk),
		 .out(out)
		 ); 

   always #5 clk = ~clk;

   always #13 in = in + 1;
   
   
   initial begin
      $dumpfile("pipeline_tb.vcd");
      $dumpvars(0, pipeline_tb);
 
      clk = 1'b0;
      reset = 1'b1;
      in = 4'b1001;
      
      #10 reset = 1'b0;

      #31 reset = 1'b1;
      #1  reset = 1'b0;
            
      #500;
      
      $finish;
      
   end

endmodule

Ch05-RTL/PipelinePattern/pipeline_tb.vcd
$date
	Sun Sep 27 16:41:50 2020
$end
$version
	Icarus Verilog
$end
$timescale
	1s
$end
$scope module pipeline_tb $end
$var wire 4 ! out [3:0] $end
$var reg 1 " clk $end
$var reg 4 # in [3:0] $end
$var reg 1 $ reset $end
$scope module uut $end
$var wire 1 " clock $end
$var wire 4 % in [3:0] $end
$var wire 1 $ reset $end
$var reg 4 & in_pipe [3:0] $end
$var reg 4 ' out [3:0] $end
$upscope $end
$upscope $end
$enddefinitions $end
#0
$dumpvars
b0 '
b0 &
b1001 %
1$
b1001 #
0"
b0 !
$end
#5
1"
#10
0"
0$
#13
b1010 #
b1010 %
#15
b1010 &
1"
#20
0"
#25
b1010 !
b1010 '
1"
#26
b1011 #
b1011 %
#30
0"
#35
b1011 &
1"
#39
b1100 #
b1100 %
#40
0"
#41
b0 &
b0 !
b0 '
1$
#42
0$
#45
b1100 &
1"
#50
0"
#52
b1101 #
b1101 %
#55
b1101 &
b1100 !
b1100 '
1"
#60
0"
#65
b1101 !
b1101 '
b1110 &
1"
b1110 #
b1110 %
#70
0"
#75
b1110 !
b1110 '
1"
#78
b1111 #
b1111 %
#80
0"
#85
b1111 &
1"
#90
0"
#91
b0 #
b0 %
#95
b0 &
b1111 !
b1111 '
1"
#100
0"
#104
b1 #
b1 %
#105
b0 !
b0 '
b1 &
1"
#110
0"
#115
b1 !
b1 '
1"
#117
b10 #
b10 %
#120
0"
#125
b10 &
1"
#130
0"
b11 #
b11 %
#135
b11 &
b10 !
b10 '
1"
#140
0"
#143
b100 #
b100 %
#145
b11 !
b11 '
b100 &
1"
#150
0"
#155
b100 !
b100 '
1"
#156
b101 #
b101 %
#160
0"
#165
b101 &
1"
#169
b110 #
b110 %
#170
0"
#175
b110 &
b101 !
b101 '
1"
#180
0"
#182
b111 #
b111 %
#185
b110 !
b110 '
b111 &
1"
#190
0"
#195
b1000 &
b111 !
b111 '
1"
b1000 #
b1000 %
#200
0"
#205
b1000 !
b1000 '
1"
#208
b1001 #
b1001 %
#210
0"
#215
b1001 &
1"
#220
0"
#221
b1010 #
b1010 %
#225
b1001 !
b1001 '
b1010 &
1"
#230
0"
#234
b1011 #
b1011 %
#235
b1011 &
b1010 !
b1010 '
1"
#240
0"
#245
b1011 !
b1011 '
1"
#247
b1100 #
b1100 %
#250
0"
#255
b1100 &
1"
#260
0"
b1101 #
b1101 %
#265
b1100 !
b1100 '
b1101 &
1"
#270
0"
#273
b1110 #
b1110 %
#275
b1110 &
b1101 !
b1101 '
1"
#280
0"
#285
b1110 !
b1110 '
1"
#286
b1111 #
b1111 %
#290
0"
#295
b1111 &
1"
#299
b0 #
b0 %
#300
0"
#305
b1111 !
b1111 '
b0 &
1"
#310
0"
#312
b1 #
b1 %
#315
b1 &
b0 !
b0 '
1"
#320
0"
#325
b1 !
b1 '
b10 &
1"
b10 #
b10 %
#330
0"
#335
b10 !
b10 '
1"
#338
b11 #
b11 %
#340
0"
#345
b11 &
1"
#350
0"
#351
b100 #
b100 %
#355
b100 &
b11 !
b11 '
1"
#360
0"
#364
b101 #
b101 %
#365
b100 !
b100 '
b101 &
1"
#370
0"
#375
b101 !
b101 '
1"
#377
b110 #
b110 %
#380
0"
#385
b110 &
1"
#390
0"
b111 #
b111 %
#395
b111 &
b110 !
b110 '
1"
#400
0"
#403
b1000 #
b1000 %
#405
b111 !
b111 '
b1000 &
1"
#410
0"
#415
b1000 !
b1000 '
1"
#416
b1001 #
b1001 %
#420
0"
#425
b1001 &
1"
#429
b1010 #
b1010 %
#430
0"
#435
b1010 &
b1001 !
b1001 '
1"
#440
0"
#442
b1011 #
b1011 %
#445
b1010 !
b1010 '
b1011 &
1"
#450
0"
#455
b1100 &
b1011 !
b1011 '
1"
b1100 #
b1100 %
#460
0"
#465
b1100 !
b1100 '
1"
#468
b1101 #
b1101 %
#470
0"
#475
b1101 &
1"
#480
0"
#481
b1110 #
b1110 %
#485
b1101 !
b1101 '
b1110 &
1"
#490
0"
#494
b1111 #
b1111 %
#495
b1111 &
b1110 !
b1110 '
1"
#500
0"
#505
b1111 !
b1111 '
1"
#507
b0 #
b0 %
#510
0"
#515
b0 &
1"
#520
0"
b1 #
b1 %
#525
b0 !
b0 '
b1 &
1"
#530
0"
#533
b10 #
b10 %
#535
b10 &
b1 !
b1 '
1"
