Ch05-RTL/Router/ibuffer.v
`timescale 100ns/10ns

module ibuffer (clk, ldata, rdata, lvalid, lrdy, rvalid, rrdy);
   input clk;
   
   input lvalid;
   output lrdy;
   input [7:0] ldata;

   input  rrdy;
   output rvalid;
   output [7:0] rdata;
 
   wire 	full, empty;
   
   reg [7:0] fifo [0:3];
   reg [7:0] irdata;
   
   reg [2:0] pnt;
   
   
   initial begin
      pnt = 3;
   end

   // assign the output values with a clk-q delay of 1:
   assign  #2 lrdy   = !full;
   assign  #2 rdata  = fifo[3]; // irdata;

   assign #2 full = pnt == 7;
   assign #2 empty = pnt == 3;
   assign    rvalid = !empty;
   assign #2 lrdy = !full;
        
   always @(posedge clk) begin
      // reading from the fifo:
      if (rrdy && !empty) begin
	 irdata = fifo[3]; //  & 8'b11111111;
	 // irdata = {fifo[3][0],fifo[3][1],fifo[3][2],fifo[3][3],fifo[3][4],fifo[3][5],fifo[3][6],fifo[3][7]};
	 
	 case (pnt)
	   7: begin 
	      fifo[3] = fifo[2];
	      fifo[2] = fifo[1];
	      fifo[1] = fifo[0];
	      pnt = 0;
	   end
	   0: begin 
	      fifo[3] = fifo[2];
	      fifo[2] = fifo[1];
	      if (lvalid && !full) begin // writing also
		 fifo[1] = ldata;
	      end
	      else // no writing
		pnt = 1;
	   end
	   1: begin 
	      fifo[3] = fifo[2];
	      if (lvalid && !full) begin // writing also
		 fifo[3'b010] = ldata;
	      end
	      else // no writing
		pnt = 2;
	   end
	   2: begin 
	      if (lvalid && !full) begin // writing also
		 fifo[3'b011] = ldata;
	      end
	      else // no writing
		pnt = 3;
	   end
	   3:  pnt = 3;
	   default: pnt = 6;
	 endcase // case (pnt)
      end // if (rrdy && !empty)
      else begin  // only writing to the fifo:
	 if (lvalid && !full) begin
	    fifo[pnt] = ldata;
	    pnt = pnt - 1;
	 end
      end // else: !if(rrdy && !empty)
      
   end
endmodule

Ch05-RTL/Router/ibuffer-synth_tb.v
`timescale 100ns/10ns

module ibuffer_tb;
   reg a, d;
   wire b, c;
   reg  [7:0] dat1;
   wire [7:0] dat2;
   reg 	     clk;

   ibuffer uut (.clk(clk), .ldata(dat1), .rdata(dat2), .lvalid(a), 
		.lrdy(b), .rvalid(c), .rrdy(d));
   
   always #10 clk <= !clk;
   
   initial begin
      $dumpfile("ibuffer-synth.vcd");
      $dumpvars(0,ibuffer_tb);
      // $dumpvars(1,ibuffer_tb.uut.fifo[0]);
      // $dumpvars(1,ibuffer_tb.uut.fifo[1]);
      // $dumpvars(1,ibuffer_tb.uut.fifo[2]);
      // $dumpvars(1,ibuffer_tb.uut.fifo[3]);
      
      a=1'b0; d=1'b0;
      clk = 1'b0;
      
      #5 a=1'b1; d=1'b1; 
      dat1 = 8'b01010101;
      #20 dat1 = dat1 + 1;
      #20 dat1 = dat1 + 1;
      #20 dat1 = dat1 + 1;
      
      d = 1'b0;
      #20 dat1 = dat1 + 1;
      #20 dat1 = dat1 + 1;
      #20 dat1 = dat1 + 1;
      
      #10 d = 1'b1;

      #10 dat1 = dat1 + 1;
      #20 dat1 = dat1 + 1;
      #20 dat1 = dat1 + 1;

      d = 1'b0;

      #20 dat1 = dat1 + 1;

      #10 d = 1'b1; a = 1'b0;

      #150 $finish;
   end
endmodule

Ch05-RTL/Router/ibuffer.vcd
$date
	Fri Jun  5 12:08:12 2020
$end
$version
	Icarus Verilog
$end
$timescale
	10ns
$end
$scope module ibuffer_tb $end
$var wire 1 ! b $end
$var wire 8 " dat2 [7:0] $end
$var wire 1 # c $end
$var reg 1 $ a $end
$var reg 1 % clk $end
$var reg 1 & d $end
$var reg 8 ' dat1 [7:0] $end
$scope module uut $end
$var wire 1 % clk $end
$var wire 8 ( ldata [7:0] $end
$var wire 1 ! lrdy $end
$var wire 1 $ lvalid $end
$var wire 8 ) rdata [7:0] $end
$var wire 1 & rrdy $end
$var wire 1 # rvalid $end
$var wire 1 * full $end
$var wire 1 + empty $end
$var reg 8 , irdata [7:0] $end
$var reg 3 - pnt [2:0] $end
$upscope $end
$upscope $end
$enddefinitions $end
#0
$dumpvars
b11 -
bx ,
1+
0*
bx )
bx (
bx '
0&
0%
0$
0#
bx "
1!
$end
#50
b1010101 '
b1010101 (
1&
1$
#100
1#
0+
b10 -
1%
#200
0%
#250
b1010110 '
b1010110 (
#300
b1010101 "
b1010101 )
b1010101 ,
1%
#400
0%
#450
b1010111 '
b1010111 (
#500
b1010110 "
b1010110 )
b1010110 ,
1%
#600
0%
#650
0#
0&
b1011000 '
b1011000 (
#700
b1 -
1%
#800
0%
#850
b1011001 '
b1011001 (
#900
b0 -
1%
#1000
0%
#1050
b1011010 '
b1011010 (
#1100
0!
1*
b111 -
1%
#1200
0%
#1250
b1011011 '
b1011011 (
#1300
1%
#1350
1#
1&
#1400
0%
#1450
b1011100 '
b1011100 (
#1500
1!
0*
b0 -
b1010111 "
b1010111 )
b1010111 ,
1%
#1600
0%
#1650
b1011101 '
b1011101 (
#1700
b1011000 "
b1011000 )
b1011000 ,
1%
#1800
0%
#1850
0#
0&
b1011110 '
b1011110 (
#1900
0!
1*
b111 -
1%
#2000
0%
#2050
b1011111 '
b1011111 (
#2100
1%
#2150
1#
0$
1&
#2200
0%
#2300
1!
0*
b0 -
b1011001 "
b1011001 )
b1011001 ,
1%
#2400
0%
#2500
b1 -
b1011010 "
b1011010 )
b1011010 ,
1%
#2600
0%
#2700
b10 -
b1011101 "
b1011101 )
b1011101 ,
1%
#2800
0%
#2900
0#
1+
b11 -
b1011110 "
b1011110 )
b1011110 ,
1%
