Ch05-RTL/Router/forward.v
`timescale 100ns/10ns

module forward (clk, lvalid, lrdy, lport, ldata,
		r0valid, r0rdy, r0data,
		r1valid, r1rdy, r1data,
		r2valid, r2rdy, r2data,
		r3valid, r3rdy, r3data );
   
   input clk;
   
   input lvalid;
   input [1:0] lport;
   input [7:0] ldata;
   output lrdy;

   input      r0rdy, r1rdy, r2rdy, r3rdy;
   output reg r0valid, r1valid, r2valid, r3valid;
   output reg [7:0] r0data, r1data, r2data, r3data;

   // Internal signals:
   reg 		    iempty;
   reg [7:0] 	    ildata;
   reg [1:0] 	    ilport;
      
   initial begin
      iempty = 1'b1; r0valid= 1'b0; r1valid = 1'b0; r2valid = 1'b0; r3valid = 1'b0; 
   end

   assign #1 lrdy = iempty;
   
   always @(posedge clk)
     begin
	if (lrdy && lvalid) begin
	   ildata = ldata;
	   ilport = lport;

	   iempty = 1'b0;
	end // if (lrdy && lvalid)


	if (iempty) begin // input register is empty:
	   if (r0valid && r0rdy)
	     r0valid = 1'b0;
	   if (r1valid && r1rdy)
	     r1valid = 1'b0;
	   if (r2valid && r2rdy)
	     r2valid = 1'b0;
	   if (r3valid && r3rdy)
	     r3valid = 1'b0;
	end

	else begin  // !iempty: input register is not empty:
	   case (lport)
	     2'b00: begin
		if (!r0valid || r0rdy) begin
		   r0data = ildata;
		   r0valid = 1'b1;
		   iempty = 1'b1;
		end
	     end
	      
	     2'b01: begin
		if (!r1valid || r1rdy) begin
		   r1data = ildata;
		   r1valid = 1'b1;
		   iempty = 1'b1;
		end
	     end
	      
	     2'b10: begin
		if (!r2valid || r2rdy) begin
		   r2data = ildata;
		   r2valid = 1'b1;
		   iempty = 1'b1;
		end
	     end
	   
	     2'b11: begin
		if (!r3valid || r3rdy) begin
		   r3data = ildata;
		   r3valid = 1'b1;
		   iempty = 1'b1;
		end
	     end
	   endcase // case (lport)
	end // if (!iempty)
     end 
   
endmodule

Ch05-RTL/Router/arbiter.v
`timescale 100ns/10ns

module arbiter (clk, rqst, port, grant);
   
   input clk;
   
   input rqst;
   output grant;
   input [1:0] port;

   reg 	       igrant;  //internal grant signal
   
   initial begin
      igrant = 1'b0;
   end

   assign #7 grant = igrant;
   
   always @(posedge clk) begin
      if (rqst)
	igrant = 1'b1;
      else
	igrant = 1'b0;
   end
 
endmodule

Ch05-RTL/Router/decoder.v
`timescale 100ns/10ns

module decoder (clk, ldata, lvalid, lrdy, 
		rdata, rvalid, rrdy, rport,
		arqst, aport, agrant);
   input clk;
   
   input lvalid;
   output lrdy;
   input [7:0] ldata;

   input  rrdy;
   output rvalid;
   output [7:0] rdata;
   output [1:0] rport;

   input 	agrant;
   output reg	arqst;
   output reg [1:0] aport;

   // Internal signals:
   reg 		    ilrdy, irvalid;
   reg [7:0] 	    irdata;
   reg [1:0] 	    irport;
   
   reg [1:0] 	outport; // output poirt number
   reg [1:0] 	decstate;  // 0: no active connection 
                           // 1: waiting for arbitration
                           // 2: connection open
   
   reg [7:0] 	inreg;  // Input register to the left
   // [7:6] ... flit type: 01 -> header flit
   //                      10 -> body flit
   //                      11 -> tail flit
   //                      00 -> no data flit

   initial begin
      outport = 2'b00;
      decstate = 0;
      ilrdy = 1'b1;

      $monitor ("(%6t; m): decstate = %b", $time, decstate);
   end

   // assign the output values with a clk-q delay of 1:
   assign #1 lrdy = ilrdy;
   assign #1 rdata = irdata;
   assign #1 rport = irport;
   assign #1 rvalid = irvalid;
           
   always @(posedge clk) begin
      case (decstate)
	0: // no active connection; a header flit may arrive
	  begin
	     if (lvalid)
	       begin
		  inreg = ldata;
		  case (ldata[7:6])
		    2'b01: // header flit
		      begin
			 arqst = 1'b1;
			 aport = ldata[5:4];
			 decstate = 1;
			 ilrdy = 1'b0;
		      end
		    default: // in this state everything else but a header flit is ignored
			 $display ("(%6t; 0.1): Unexpected flit type: ldata = %b", $time, ldata);
		  endcase // case (ldata[7:6])
	       end // if (lvalid)
	  end // case: 0
	
	1: // waiting for arbitration:
	  begin
	     if (agrant)
	       begin
		  arqst = 1'b0;
		  decstate = 2;
		  if (rrdy)
		    begin
		       outport = inreg[5:4];
		       irport =  inreg[5:4];
		       irdata = inreg;
		       irvalid = 1'b1;
		       ilrdy = 1'b1;
		    end
		  if (lvalid)
		    begin
		       case (ldata[7:6])
			 2'b01: // header flit:
			   $display ("(%6t; %d.1): Unexpected flit type: ldata = %b", $time, decstate, ldata);
			 2'b10, // body flit:
			   2'b11: // tail flit:
			     inreg = ldata;
			 2'b01: // no data flit:
			   $display ("(%6t; %d.2): Unexpected flit type: ldata = %b", $time, decstate, ldata);
		       endcase
		    end // if (lvalid)
		  
	       end // if (agrant)
	  end // case: 1
	
	2: // Connection is open:
	  begin
	     if (rrdy)
	       ilrdy = 1'b1;
	     else  // if right output is not ready, we stop left input:
	       ilrdy = 1'b0;
	     
	     irdata = inreg;
	     irport = outport;
	     irvalid = 1'b1;
	     case (inreg[7:6])
	       2'b11: // tail flit:
		 begin
		    if (lvalid)
		      begin
		  	 inreg = ldata;
		  	 case (ldata[7:6])
		  	   2'b01: 
		  	     begin
		  		arqst = 1'b1;
		  		aport = ldata[5:4];
		  		decstate = 1; 
				ilrdy = 1'b0;
		  	     end
		  	   default: $display("(%6t; 2.1): Unexpected flit type: ldate = %b", $time, ldata);
		  	 endcase // case (ldata[7:6])
		      end // if (lvalid)

		    else // tail flit has passed; no new header flit has arrived:
		      begin
		  	 decstate = 0;
		  	 arqst = 1'b0;
		      end // else: !if(lvalid)
		 end // case: 2'b11
		    
	       2'b00, 2'b01: // header flit or no data flit are not okay:
		 $display("(%6t; 2.2): Unexpected flit type: ldate = %b", $time, ldata);
	       
	       2'b10: // body flit is ok.
		 begin
		    if (lvalid)
		      inreg = ldata;
		 end
		    
	     endcase // case (inreg[7:6])

	  end	     
	default: $display("(%6t; 3): Unexpected decstate: decstate = %d", $time, decstate);
      endcase // case (decstate)
      
      
   end
   
endmodule

Ch05-RTL/Router/ibuffer.v
`timescale 100ns/10ns

module ibuffer (clk, ldata, rdata, lvalid, lrdy, rvalid, rrdy);
   input clk;
   
   input lvalid;
   output lrdy;
   input [7:0] ldata;

   input  rrdy;
   output rvalid;
   output [7:0] rdata;
 
   wire 	full, empty;
   
   reg [7:0] fifo [0:3];
   reg [7:0] irdata;
   
   reg [2:0] pnt;
   
   
   initial begin
      pnt = 3;
   end

   // assign the output values with a clk-q delay of 1:
   assign  #2 lrdy   = !full;
   assign  #2 rdata  = fifo[3]; // irdata;

   assign #2 full = pnt == 7;
   assign #2 empty = pnt == 3;
   assign    rvalid = !empty;
   assign #2 lrdy = !full;
        
   always @(posedge clk) begin
      // reading from the fifo:
      if (rrdy && !empty) begin
	 irdata = fifo[3]; //  & 8'b11111111;
	 // irdata = {fifo[3][0],fifo[3][1],fifo[3][2],fifo[3][3],fifo[3][4],fifo[3][5],fifo[3][6],fifo[3][7]};
	 
	 case (pnt)
	   7: begin 
	      fifo[3] = fifo[2];
	      fifo[2] = fifo[1];
	      fifo[1] = fifo[0];
	      pnt = 0;
	   end
	   0: begin 
	      fifo[3] = fifo[2];
	      fifo[2] = fifo[1];
	      if (lvalid && !full) begin // writing also
		 fifo[1] = ldata;
	      end
	      else // no writing
		pnt = 1;
	   end
	   1: begin 
	      fifo[3] = fifo[2];
	      if (lvalid && !full) begin // writing also
		 fifo[3'b010] = ldata;
	      end
	      else // no writing
		pnt = 2;
	   end
	   2: begin 
	      if (lvalid && !full) begin // writing also
		 fifo[3'b011] = ldata;
	      end
	      else // no writing
		pnt = 3;
	   end
	   3:  pnt = 3;
	   default: pnt = 6;
	 endcase // case (pnt)
      end // if (rrdy && !empty)
      else begin  // only writing to the fifo:
	 if (lvalid && !full) begin
	    fifo[pnt] = ldata;
	    pnt = pnt - 1;
	 end
      end // else: !if(rrdy && !empty)
      
   end
endmodule

Ch05-RTL/Router/router_tb.v
`timescale 100ns/10ns

module router_tb;
   reg lvalid;
   wire lrdy, arqst, agrant;
   reg  [7:0] ldata;
   wire [1:0] aport;

   wire       s1valid, s1rdy;
   wire [7:0] s1data;

   wire       s2valid, s2rdy;
   wire [1:0] s2port;
   wire [7:0] s2data;

   wire       r0valid, r1valid, r2valid, r3valid;
   reg 	      r0rdy, r1rdy, r2rdy, r3rdy;
   wire [7:0] r0data, r1data, r2data, r3data;
   
   reg 	     clk;

   ibuffer uut1 (.clk(clk), .ldata(ldata), .lrdy(lrdy), .lvalid(lvalid),
		 .rdata(s1data), .rvalid(s1valid), .rrdy(s1rdy));
   
   decoder uut2 (.clk(clk), 
		 .ldata(s1data), .lvalid(s1valid), .lrdy(s1rdy), 
		 .rdata(s2data), .rvalid(s2valid), .rrdy(s2rdy), .rport(s2port),
		 .arqst(arqst), .aport(aport), .agrant(agrant));

   arbiter uut3 (.clk(clk), .rqst(arqst), .port(aport), .grant(agrant));

   forward uut4 (.clk(clk), .lvalid(s2valid), .lrdy(s2rdy), .lport(s2port), .ldata(s2data),
		 .r0valid(r0valid), .r0rdy(r0rdy), .r0data(r0data),
		 .r1valid(r1valid), .r1rdy(r1rdy), .r1data(r1data),
		 .r2valid(r2valid), .r2rdy(r2rdy), .r2data(r2data),
		 .r3valid(r3valid), .r3rdy(r3rdy), .r3data(r3data));
   
		 
   always #10 clk <= !clk;
   
   initial begin
      $dumpfile("router.vcd");
      $dumpvars(0,router_tb);
      // $dumpvars(1,ibuffer_tb.uut.fifo[0]);
      // $dumpvars(1,ibuffer_tb.uut.fifo[1]);
      // $dumpvars(1,ibuffer_tb.uut.fifo[2]);
      // $dumpvars(1,ibuffer_tb.uut.fifo[3]);

      $timeformat(-6, 0, " us", 10);
            
      clk = 1'b0;
      lvalid = 1'b0;
      r0rdy = 1'b1; r1rdy = 1'b1; r2rdy = 1'b1; r3rdy = 1'b1;
      ldata = 8'b00000000;
      
      #5 lvalid=1'b1; ldata = 8'b01010101;

      
      #20 ldata = 8'b10010110;

      #20 ldata = 8'b10010111;
      
      #20 ldata = 8'b10011000;
      
      #20 ldata = 8'b10011001; r1rdy = 1'b0;
      
      #20 ldata = 8'b11011010; r1rdy = 1'b1;
       
      #20 lvalid = 1'b0;

      // 
      #20 lvalid=1'b1; ldata = 8'b01110101;

      
      #20 ldata = 8'b10110110;

      #20 ldata = 8'b10110111;
      
      #20 ldata = 8'b10111000;
      
      #20 ldata = 8'b10111001;

      #20 ldata = 8'b11111010;
 
      #20 lvalid = 1'b0;
      #150 $finish;
   end
endmodule

Ch05-RTL/Router/router.vcd
$date
	Wed Jun 10 11:32:40 2020
$end
$version
	Icarus Verilog
$end
$timescale
	10ns
$end
$scope module router_tb $end
$var wire 1 ! lrdy $end
$var wire 1 " s2valid $end
$var wire 1 # s2rdy $end
$var wire 2 $ s2port [1:0] $end
$var wire 8 % s2data [7:0] $end
$var wire 1 & s1valid $end
$var wire 1 ' s1rdy $end
$var wire 8 ( s1data [7:0] $end
$var wire 1 ) r3valid $end
$var wire 8 * r3data [7:0] $end
$var wire 1 + r2valid $end
$var wire 8 , r2data [7:0] $end
$var wire 1 - r1valid $end
$var wire 8 . r1data [7:0] $end
$var wire 1 / r0valid $end
$var wire 8 0 r0data [7:0] $end
$var wire 1 1 arqst $end
$var wire 2 2 aport [1:0] $end
$var wire 1 3 agrant $end
$var reg 1 4 clk $end
$var reg 8 5 ldata [7:0] $end
$var reg 1 6 lvalid $end
$var reg 1 7 r0rdy $end
$var reg 1 8 r1rdy $end
$var reg 1 9 r2rdy $end
$var reg 1 : r3rdy $end
$scope module uut1 $end
$var wire 1 4 clk $end
$var wire 8 ; ldata [7:0] $end
$var wire 1 ! lrdy $end
$var wire 1 6 lvalid $end
$var wire 8 < rdata [7:0] $end
$var wire 1 & rvalid $end
$var wire 1 ' rrdy $end
$var wire 1 = full $end
$var wire 1 > empty $end
$var reg 8 ? irdata [7:0] $end
$var reg 3 @ pnt [2:0] $end
$upscope $end
$scope module uut2 $end
$var wire 1 4 clk $end
$var wire 8 A ldata [7:0] $end
$var wire 1 ' lrdy $end
$var wire 1 & lvalid $end
$var wire 8 B rdata [7:0] $end
$var wire 2 C rport [1:0] $end
$var wire 1 " rvalid $end
$var wire 1 # rrdy $end
$var wire 1 3 agrant $end
$var reg 2 D aport [1:0] $end
$var reg 1 1 arqst $end
$var reg 2 E decstate [1:0] $end
$var reg 1 F ilrdy $end
$var reg 8 G inreg [7:0] $end
$var reg 8 H irdata [7:0] $end
$var reg 2 I irport [1:0] $end
$var reg 1 J irvalid $end
$var reg 2 K outport [1:0] $end
$upscope $end
$scope module uut3 $end
$var wire 1 4 clk $end
$var wire 1 3 grant $end
$var wire 2 L port [1:0] $end
$var wire 1 1 rqst $end
$var reg 1 M igrant $end
$upscope $end
$scope module uut4 $end
$var wire 1 4 clk $end
$var wire 8 N ldata [7:0] $end
$var wire 2 O lport [1:0] $end
$var wire 1 # lrdy $end
$var wire 1 " lvalid $end
$var wire 1 7 r0rdy $end
$var wire 1 8 r1rdy $end
$var wire 1 9 r2rdy $end
$var wire 1 : r3rdy $end
$var reg 1 P iempty $end
$var reg 8 Q ildata [7:0] $end
$var reg 2 R ilport [1:0] $end
$var reg 8 S r0data [7:0] $end
$var reg 1 / r0valid $end
$var reg 8 T r1data [7:0] $end
$var reg 1 - r1valid $end
$var reg 8 U r2data [7:0] $end
$var reg 1 + r2valid $end
$var reg 8 V r3data [7:0] $end
$var reg 1 ) r3valid $end
$upscope $end
$upscope $end
$enddefinitions $end
#0
$dumpvars
bx V
bx U
bx T
bx S
bx R
bx Q
1P
bx O
bx N
0M
bx L
b0 K
xJ
bx I
bx H
bx G
1F
b0 E
bx D
bx C
bx B
bx A
b11 @
bx ?
x>
x=
bx <
b0 ;
1:
19
18
17
06
b0 5
04
x3
bx 2
x1
bx 0
0/
bx .
0-
bx ,
0+
bx *
0)
bx (
x'
x&
bx %
bx $
x#
x"
x!
$end
#10
1#
1'
#20
0=
0&
1>
#40
1!
#50
b1010101 5
b1010101 ;
16
#70
03
#100
b10 @
14
#120
1&
0>
b1010101 (
b1010101 <
b1010101 A
#200
04
#250
b10010110 5
b10010110 ;
#300
1M
0F
b1 E
b1 2
b1 D
b1 L
11
b1010101 G
b1010101 ?
14
#310
0'
#320
b10010110 (
b10010110 <
b10010110 A
#370
13
#400
04
#450
b10010111 5
b10010111 ;
#500
b1 @
b10010110 G
1F
1J
b1010101 H
b1 I
b1 K
b10 E
01
14
#510
1'
1"
b1010101 %
b1010101 B
b1010101 N
b1 $
b1 C
b1 O
#600
04
#650
b10011000 5
b10011000 ;
#700
1-
b1010101 .
b1010101 T
1P
b1 R
b1010101 Q
0M
b10010110 H
b10010110 ?
14
#710
b10010110 %
b10010110 B
b10010110 N
#720
b10010111 (
b10010111 <
b10010111 A
#770
03
#800
04
#850
08
b10011001 5
b10011001 ;
#900
b10010111 ?
b10010111 G
0P
b10010110 Q
14
#910
0#
#920
b10011000 (
b10011000 <
b10011000 A
#1000
04
#1050
18
b11011010 5
b11011010 ;
#1100
1P
b10010110 .
b10010110 T
b10011000 G
b10010111 H
0F
b10011000 ?
14
#1110
1#
b10010111 %
b10010111 B
b10010111 N
0'
#1120
b10011001 (
b10011001 <
b10011001 A
#1200
04
#1250
06
#1300
b10011001 G
b10011000 H
1F
b10010111 .
b10010111 T
1P
b10010111 Q
14
#1310
b10011000 %
b10011000 B
b10011000 N
1'
#1400
04
#1450
b1110101 5
b1110101 ;
16
#1500
b10011000 .
b10011000 T
1P
b10011000 Q
b10011001 H
b10011001 ?
14
#1510
b10011001 %
b10011001 B
b10011001 N
#1520
b11011010 (
b11011010 <
b11011010 A
#1600
04
#1650
b10110110 5
b10110110 ;
#1700
b11011010 ?
b11011010 G
b10011001 .
b10011001 T
1P
b10011001 Q
14
#1720
b1110101 (
b1110101 <
b1110101 A
#1800
04
#1850
b10110111 5
b10110111 ;
#1900
1P
1M
0F
b1 E
b11 2
b11 D
b11 L
11
b1110101 G
b11011010 H
b1110101 ?
14
#1910
0'
b11011010 %
b11011010 B
b11011010 N
#1920
b10110110 (
b10110110 <
b10110110 A
#1970
13
#2000
04
#2050
b10111000 5
b10111000 ;
#2100
b0 @
b10110110 G
1F
b1110101 H
b11 I
b11 K
b10 E
01
b11011010 .
b11011010 T
1P
b11011010 Q
14
#2110
1'
b1110101 %
b1110101 B
b1110101 N
b11 $
b11 C
b11 O
#2200
04
#2250
b10111001 5
b10111001 ;
#2300
1)
b1110101 *
b1110101 V
1P
b11 R
b1110101 Q
0M
b10110110 H
b10110110 ?
14
#2310
b10110110 %
b10110110 B
b10110110 N
#2320
b10110111 (
b10110111 <
b10110111 A
#2370
03
#2400
04
#2450
b11111010 5
b11111010 ;
#2500
b10110111 ?
b10110111 G
b10110110 *
b10110110 V
1P
b10110110 Q
14
#2520
b10111000 (
b10111000 <
b10111000 A
#2600
04
#2650
06
#2700
1P
b10111000 G
b10110111 H
b1 @
b10111000 ?
14
#2710
b10110111 %
b10110111 B
b10110111 N
#2720
b10111001 (
b10111001 <
b10111001 A
#2800
04
#2900
b10 @
b10111001 ?
b10111001 G
b10111000 H
b10110111 *
b10110111 V
1P
b10110111 Q
14
#2910
b10111000 %
b10111000 B
b10111000 N
#2920
b11111010 (
b11111010 <
b11111010 A
#3000
04
#3100
b10111000 *
b10111000 V
1P
b10111000 Q
b11111010 G
b10111001 H
b11 @
b11111010 ?
14
#3110
b10111001 %
b10111001 B
b10111001 N
#3120
0&
1>
#3200
04
#3300
b0 E
b11111010 H
b10111001 *
b10111001 V
1P
b10111001 Q
14
#3310
b11111010 %
b11111010 B
b11111010 N
#3400
04
#3500
b11111010 *
b11111010 V
1P
b11111010 Q
14
#3600
04
#3700
1P
14
#3800
04
#3900
1P
14
#4000
04
#4100
1P
14
