Ch03-ModelingBasics/FullAdder/TruthTable/fulladderTT.v

module fulladderTT (a,b, ci, sum, co);
   input a,b,ci;
   output sum, co;
   wire [2:0] ivec;
   reg [1:0] ovec;

   assign ivec = {a,b,ci};
      
   always @ (a or b or ci)
     case (ivec)
       3'b000 : ovec=2'b00;
       3'b001 : ovec=2'b01;
       3'b010 : ovec=2'b01;
       3'b011 : ovec=2'b10;
       3'b100 : ovec=2'b01;
       3'b101 : ovec=2'b10;
       3'b110 : ovec=2'b10;
       3'b111 : ovec=2'b11;
       default: ovec=2'b11; 
     endcase 
   
   assign {co,sum} = ovec;
endmodule

Ch03-ModelingBasics/FullAdder/fulladder_tb.v

`timescale 100ps/10ps

module fulladder_tb;
   reg a, b, ci;
   wire sum, carry;

   fulladderTT uut (.a(a), .b(b), .ci(ci), .sum(sum), .co(carry));

   initial begin
      $dumpfile("fulladder_tb.vcd");
      $dumpvars(0,fulladder_tb);
      
      #10 a=1'b0; b=1'b0; ci=1'b0;

      #10 a=1'b0; b=1'b1; ci = 1'b0;
      #10 a=1'b0; b=1'b1; ci = 1'b1;

      #10 a=1'b1; b=1'b0; ci = 1'b0;
      #10 a=1'b1; b=1'b0; ci = 1'b1;

      #10 a=1'b1; b=1'b1;ci = 1'b0;
      #10 a=1'b1; b=1'b1;ci = 1'b1;

      #10 $finish;
   end
endmodule

Ch03-ModelingBasics/FullAdder/TruthTable/fulladder_tb.vcd
$date
	Sat Sep 19 16:21:19 2020
$end
$version
	Icarus Verilog
$end
$timescale
	10ps
$end
$scope module fulladder_tb $end
$var wire 1 ! sum $end
$var wire 1 " carry $end
$var reg 1 # a $end
$var reg 1 $ b $end
$var reg 1 % ci $end
$scope module uut $end
$var wire 1 # a $end
$var wire 1 $ b $end
$var wire 1 % ci $end
$var wire 1 ! sum $end
$var wire 3 & ivec [2:0] $end
$var wire 1 " co $end
$var reg 2 ' ovec [1:0] $end
$upscope $end
$upscope $end
$enddefinitions $end
#0
$dumpvars
bx '
bx &
x%
x$
x#
x"
x!
$end
#100
0"
0!
b0 '
0%
0$
b0 &
0#
#200
1!
b1 '
b10 &
1$
#300
1"
0!
b10 '
b11 &
1%
#400
0"
1!
b1 '
0%
0$
b100 &
1#
#500
1"
0!
b10 '
b101 &
1%
#600
0%
b110 &
1$
#700
1!
b11 '
b111 &
1%
