Ch05-RTL/Multiplier-CarrySave/Pipelined-0/multiplier-Pipelined-0-48b.v
module multiplier(a, b, y, clk);

   parameter width = 48;
   input [width-1:0] a, b;
   output [2*width-1:0] y;
      // output  y;
   input 	      clk;

   reg [width-1:0]    areg, breg;
   reg [width-1:0]    partialsa [width-1:0];
   reg [width-1:0]    partialsb [width-1:0];
   reg [width-1:0]    partialss [width-1:0];
   reg [width-1:0]    partialsci [width-1:0];
   reg [width-1:0]    partialsco [width-1:0];

   reg [width-1:0]    lrows, lrowco;
   
   reg [2*width-1:0]  yi;
   
   // genvar 		  i;
   // assign partials[width-1 : 0] = a[0] ? b : 0;
   // generate for (i = 1; i < width; i = i+1) begin:gen
   //    assign partials[width*(i+1)-1 : width*i] = (a[i] ? b << i : 0) +
   // 						 partials[width*i-1 : width*(i-1)];
   // end endgenerate

   // assign y = partials[width*width-1 : width*(width-1)];

   integer 	      i;



   // Input registers:
   always @(posedge clk) begin
      areg = a;
      breg = b;
   end

   // No pipelining:   
   always @(posedge clk) begin

      partialsa[0] = 0;
      partialsb[0] = areg[0] ? breg : 0;
      partialsci[0] = 0;

      partialss[0] = partialsa[0] ^ partialsb[0] ^ partialsci[0];
      partialsco[0] = (partialsa[0] & partialsb[0]) 
	| (partialsa[0] & partialsci[0])
	  | (partialsb[0] & partialsci[0]);
      yi[0] = partialss[0][0];
      
      for (i = 1; i < width; i = i+1) begin
	 partialsa[i]  = partialss[i-1] >> 1;
	 partialsb[i]  = areg[i] ? (breg): 0;
	 partialsci[i] = partialsco[i-1];
	 	 
	 partialss[i] = partialsa[i] ^ partialsb[i] ^ partialsci[i];
	 partialsco[i] = (partialsa[i] & partialsb[i]) 
	   | (partialsa[i] & partialsci[i])
	     | (partialsb[i] & partialsci[i]);
	 yi[i] = partialss[i][0];
      end

      // Last summation row:
      yi[width] = partialsco[width-1][0] ^ partialss[width-1][1];
      lrowco[0] = partialsco[width-1][0] & partialss[width-1][1];
      
      for (i = 1; i < width-1; i = i+1) begin
	 yi[i+width] = partialsco[width-1][i] ^ partialss[width-1][i+1] ^ lrowco[i-1];
	 lrowco[i] = (partialsco[width-1][i] & partialss[width-1][i+1])
	   | (partialsco[width-1][i] & lrowco[i-1])
	     |  (partialss[width-1][i+1] & lrowco[i-1]);
	 end

      yi[2*width-1] = partialsco[width-1][width-1] ^ lrowco[width-2];
      lrowco[width-1] = partialsco[width-1][width-1] & lrowco[width-2];
      
   end

   
   assign #1 y = yi;
         
endmodule // multiplier

Ch05-RTL/Multiplier-CarrySave/Pipelined-0/multiplier_tb.v

module multiplier_tb;

   parameter width = 16;
   
   reg [width-1:0] a, b;
   wire [2*width-1:0] y;
   reg [2*width-1:0]  yfull, yprev;
   
   
   reg 	       clk;
   
   
   multiplier #(
		.width(width)
		) uut (
		       .a(a),
		       .b(b),
		       .y(y),
		       .clk(clk)
		       ); 

   reg [width-1:0]  xrnd = 9;
   task xorshift32;
      begin
	 xrnd = xrnd ^ (xrnd << (width*3/12));
	 xrnd = xrnd ^ (xrnd >> (width/2));
	 xrnd = xrnd ^ (xrnd << (width*3/4));
	 xrnd = xrnd ^ (xrnd >> (width*3/12));
	 xrnd = xrnd ^ (xrnd >> (3));
	 xrnd = xrnd ^ (xrnd << (13));
      end endtask

   integer i;

   always #5 clk = ~clk;
   
   initial begin
      $dumpfile("multiplier_tb.vcd");
      $dumpvars(1,multiplier_tb.uut.partialsa[0]);
      $dumpvars(1,multiplier_tb.uut.partialsa[1]);
      $dumpvars(1,multiplier_tb.uut.partialsa[2]);
      $dumpvars(1,multiplier_tb.uut.partialsa[3]);

      $dumpvars(1,multiplier_tb.uut.partialsb[0]);
      $dumpvars(1,multiplier_tb.uut.partialsb[1]);
      $dumpvars(1,multiplier_tb.uut.partialsb[2]);
      $dumpvars(1,multiplier_tb.uut.partialsb[3]);

      $dumpvars(1,multiplier_tb.uut.partialss[0]);
      $dumpvars(1,multiplier_tb.uut.partialss[1]);
      $dumpvars(1,multiplier_tb.uut.partialss[2]);    
      $dumpvars(1,multiplier_tb.uut.partialss[3]);

      $dumpvars(1,multiplier_tb.uut.partialsco[0]);
      $dumpvars(1,multiplier_tb.uut.partialsco[1]);
      $dumpvars(1,multiplier_tb.uut.partialsco[2]);
      $dumpvars(1,multiplier_tb.uut.partialsco[3]);
      // $dumpvars(1,multiplier_tb.uut.preg[3]);
      // $dumpvars(1,multiplier_tb.uut.preg[5]);
      // $dumpvars(1,multiplier_tb.uut.preg[7]);
      $dumpvars(0, multiplier_tb);
 
      clk = 1'b0;
      
      for (i = 0; i < 100; i = i+1)
	begin
	   #1;

	   xorshift32;
	   a <= xrnd;
	   xorshift32;
	   b <= xrnd;

	   #1;
	   
	   yfull = a*b;
	   #8;

	   $display("%d * %d = %d (%d; %d)", a, b, y, yfull, yprev);
	   if (yprev != y) begin
	      $display("ERROR!");
	      $finish;
	   end

	   yprev = yfull;
	   
	end // for (i = 0; i < 100; i = i+1)

      a = 8'b11111111;
      b = 8'b11111111;

      #5;
      
      $display("PASSED.");
      $finish;
      
   end

endmodule

Ch05-RTL/Multiplier-CarrySave/Pipelined-0/multiplier_tb.vcd
$date
	Fri Jul 17 14:53:35 2020
$end
$version
	Icarus Verilog
$end
$timescale
	1s
$end
$scope module multiplier_tb $end
$scope module uut $end
$var reg 16 ! \partialsa[0] [15:0] $end
$upscope $end
$upscope $end
$scope module multiplier_tb $end
$scope module uut $end
$var reg 16 " \partialsa[1] [15:0] $end
$upscope $end
$upscope $end
$scope module multiplier_tb $end
$scope module uut $end
$var reg 16 # \partialsa[2] [15:0] $end
$upscope $end
$upscope $end
$scope module multiplier_tb $end
$scope module uut $end
$var reg 16 $ \partialsa[3] [15:0] $end
$upscope $end
$upscope $end
$scope module multiplier_tb $end
$scope module uut $end
$var reg 16 % \partialsb[0] [15:0] $end
$upscope $end
$upscope $end
$scope module multiplier_tb $end
$scope module uut $end
$var reg 16 & \partialsb[1] [15:0] $end
$upscope $end
$upscope $end
$scope module multiplier_tb $end
$scope module uut $end
$var reg 16 ' \partialsb[2] [15:0] $end
$upscope $end
$upscope $end
$scope module multiplier_tb $end
$scope module uut $end
$var reg 16 ( \partialsb[3] [15:0] $end
$upscope $end
$upscope $end
$scope module multiplier_tb $end
$scope module uut $end
$var reg 16 ) \partialss[0] [15:0] $end
$upscope $end
$upscope $end
$scope module multiplier_tb $end
$scope module uut $end
$var reg 16 * \partialss[1] [15:0] $end
$upscope $end
$upscope $end
$scope module multiplier_tb $end
$scope module uut $end
$var reg 16 + \partialss[2] [15:0] $end
$upscope $end
$upscope $end
$scope module multiplier_tb $end
$scope module uut $end
$var reg 16 , \partialss[3] [15:0] $end
$upscope $end
$upscope $end
$scope module multiplier_tb $end
$scope module uut $end
$var reg 16 - \partialsco[0] [15:0] $end
$upscope $end
$upscope $end
$scope module multiplier_tb $end
$scope module uut $end
$var reg 16 . \partialsco[1] [15:0] $end
$upscope $end
$upscope $end
$scope module multiplier_tb $end
$scope module uut $end
$var reg 16 / \partialsco[2] [15:0] $end
$upscope $end
$upscope $end
$scope module multiplier_tb $end
$scope module uut $end
$var reg 16 0 \partialsco[3] [15:0] $end
$upscope $end
$upscope $end
$scope module multiplier_tb $end
$var wire 32 1 y [31:0] $end
$var reg 16 2 a [15:0] $end
$var reg 16 3 b [15:0] $end
$var reg 1 4 clk $end
$var reg 16 5 xrnd [15:0] $end
$var reg 32 6 yfull [31:0] $end
$var reg 32 7 yprev [31:0] $end
$var integer 32 8 i [31:0] $end
$scope module uut $end
$var wire 16 9 a [15:0] $end
$var wire 16 : b [15:0] $end
$var wire 1 4 clk $end
$var wire 32 ; y [31:0] $end
$var reg 16 < areg [15:0] $end
$var reg 16 = breg [15:0] $end
$var reg 16 > lrowco [15:0] $end
$var reg 32 ? yi [31:0] $end
$var integer 32 @ i [31:0] $end
$upscope $end
$scope task xorshift32 $end
$upscope $end
$upscope $end
$enddefinitions $end
#0
$dumpvars
bx @
bx ?
bx >
bx =
bx <
bx ;
bx :
bx 9
b0 8
bx 7
bx 6
b1001 5
04
bx 3
bx 2
bx 1
bx 0
bx /
bx .
bx -
bx ,
bx +
bx *
bx )
bx (
bx '
bx &
bx %
bx $
bx #
bx "
bx !
$end
#1
b110110001110001 3
b110110001110001 :
b1100101010100010 2
b1100101010100010 9
b110110001110001 5
#2
b1010101110101011100100110000010 6
#5
b110110001110001 =
b1100101010100010 <
b0xxxxxxxxxxxxxxx >
b0xxxxxxxxxxxxxxx 0
bx ,
bx (
b0xxxxxxxxxxxxxxx $
b0xxxxxxxxxxxxxxx /
bx +
bx '
b0xxxxxxxxxxxxxxx #
b0xxxxxxxxxxxxxxx .
bx *
bx &
b0xxxxxxxxxxxxxxx "
b1111 @
b0 -
bx )
bx %
b0 !
14
#10
04
b1 8
b1010101110101011100100110000010 7
#11
b1000000011010000 3
b1000000011010000 :
b101000011000 2
b101000011000 9
b1000000011010000 5
#12
b101000101000011001110000000 6
#15
b1000000011010000 =
b101000011000 <
b10100001100000 >
b0 0
b1101100011100 ,
b0 (
b1101100011100 $
b0 /
b11011000111000 +
b0 '
b11011000111000 #
b0 .
b110110001110001 *
b110110001110001 &
b0 "
b1111 @
b1010101110101011100100110000010 ?
b0 -
b0 )
b0 %
b0 !
14
#16
b1010101110101011100100110000010 1
b1010101110101011100100110000010 ;
#20
04
b10 8
b101000101000011001110000000 7
#21
b1001001011011 3
b1001001011011 :
b111001110011001 2
b111001110011001 9
b1001001011011 5
#22
b1000010010011101100101100011 6
#25
b1001001011011 =
b111001110011001 <
b0 >
b0 0
b1000000011010000 ,
b1000000011010000 (
b0 $
b0 /
b0 +
b0 '
b0 #
b101000101000011001110000000 ?
b0 .
b0 *
b0 &
b0 "
b1111 @
b0 -
b0 )
b0 %
b0 !
14
#26
b101000101000011001110000000 1
b101000101000011001110000000 ;
#30
04
b11 8
b1000010010011101100101100011 7
#31
b111001011010110 3
b111001011010110 :
b100011110110101 2
b100011110110101 9
b111001011010110 5
#32
b100000001010101000101101001110 6
#35
b111001011010110 =
b100011110110101 <
b11000110000 >
b1001001011 0
b1000000010000 ,
b1001001011011 (
b1001001011 $
b0 /
b10010010110 +
b0 '
b10010010110 #
b0 .
b100100101101 *
b0 &
b100100101101 "
b1111 @
b1000010010011101100101100011 ?
b0 -
b1001001011011 )
b1001001011011 %
b0 !
14
#36
b1000010010011101100101100011 1
b1000010010011101100101100011 ;
#40
04
b100 8
b100000001010101000101101001110 7
#41
b11001000000011 3
b11001000000011 :
b111101101110101 2
b111101101110101 9
b11001000000011 5
#42
b11000000111100100110001011111 6
#45
b11001000000011 =
b111101101110101 <
b1111110000000 >
b1000000010000 0
b10011110100101 ,
b0 (
b11011100110001 $
b1000010010100 /
b110111001100011 +
b111001011010110 '
b1110010110101 #
b0 .
b11100101101011 *
b0 &
b11100101101011 "
b1111 @
b100000001010101000101101001110 ?
b0 -
b111001011010110 )
b111001011010110 %
b0 !
14
#46
b100000001010101000101101001110 1
b100000001010101000101101001110 ;
#50
04
b101 8
b11000000111100100110001011111 7
#51
b1001010110111100 3
b1001010110111100 :
b110001001000011 2
b110001001000011 9
b1001010110111100 5
#52
b111001011110010010100000110100 6
#55
b1001010110111100 =
b110001001000011 <
b11000000001 >
b0 0
b1111101000001 ,
b0 (
b1111101000001 $
b0 /
b11111010000011 +
b11001000000011 '
b110010000000 #
b0 .
b1100100000001 *
b0 &
b1100100000001 "
b1111 @
b11000000111100100110001011111 ?
b0 -
b11001000000011 )
b11001000000011 %
b0 !
14
#56
b11000000111100100110001011111 1
b11000000111100100110001011111 ;
#60
04
b110 8
b111001011110010010100000110100 7
#61
b1101110100101000 3
b1101110100101000 :
b1011110001010010 2
b1011110001010010 9
b1101110100101000 5
#62
b10100010101100000011011011010000 6
#65
b1101110100101000 =
b1011110001010010 <
b10000000100 >
b10010000 0
b11011100000110 ,
b0 (
b11011110010110 $
b10010000 /
b110111100101101 +
b0 '
b110111110110001 #
b10011100 .
b1101111101100010 *
b1001010110111100 &
b100101011011110 "
b1111 @
b111001011110010010100000110100 ?
b0 -
b1001010110111100 )
b1001010110111100 %
b0 !
14
#66
b111001011110010010100000110100 1
b111001011110010010100000110100 ;
#70
04
b111 8
b10100010101100000011011011010000 7
#71
b1001101110000000 3
b1001101110000000 :
b1011011101010110 2
b1011011101010110 9
b1001101110000000 5
#72
b1101111010111001011110100000000 6
#75
b1001101110000000 =
b1011011101010110 <
b101110100001000 >
b0 0
b11011101001010 ,
b0 (
b11011101001010 $
b10100010101100000011011011010000 ?
b0 /
b110111010010100 +
b0 '
b110111010010100 #
b0 .
b1101110100101000 *
b1101110100101000 &
b0 "
b1111 @
b0 -
b0 )
b0 %
b0 !
14
#76
b10100010101100000011011011010000 1
b10100010101100000011011011010000 ;
#80
04
b1000 8
b1101111010111001011110100000000 7
#81
b101100000001011 3
b101100000001011 :
b101000011001010 2
b101000011001010 9
b101100000001011 5
#82
b11011110010001110100010101110 6
#85
b101100000001011 =
b101000011001010 <
b1000000000000 >
b1101111010111001011110100000000 ?
b100100000000 0
b110001010100000 ,
b0 (
b110101100100000 $
b100110000000 /
b1101011001000000 +
b1001101110000000 '
b100110111000000 #
b0 .
b1001101110000000 *
b1001101110000000 &
b0 "
b1111 @
b0 -
b0 )
b0 %
b0 !
14
#86
b1101111010111001011110100000000 1
b1101111010111001011110100000000 ;
#90
04
b1001 8
b11011110010001110100010101110 7
#91
b1111000110000100 3
b1111000110000100 :
b1101101000111001 2
b1101101000111001 9
b1111000110000100 5
#92
b11001101111000000010111001100100 6
#95
b1111000110000100 =
b1101101000111001 <
b110 >
b1000000000010 0
b100111000001001 ,
b101100000001011 (
b1011000000010 $
b0 /
b10110000000101 +
b0 '
b10110000000101 #
b11011110010001110100010101110 ?
b0 .
b101100000001011 *
b101100000001011 &
b0 "
b1111 @
b0 -
b0 )
b0 %
b0 !
14
#96
b11011110010001110100010101110 1
b11011110010001110100010101110 ;
#100
04
b1010 8
b11001101111000000010111001100100 7
#101
b1111110001100101 3
b1111110001100101 :
b11110111101000 2
b11110111101000 9
b1111110001100101 5
#102
b111101000010001100110010001000 6
#105
b1111110001100101 =
b11110111101000 <
b111000000011100 >
b1000000000000 0
b1110111110110100 ,
b1111000110000100 (
b1111000110000 $
b0 /
b11110001100001 +
b0 '
b11110001100001 #
b11001101111000000010111001100100 ?
b0 .
b111100011000010 *
b0 &
b111100011000010 "
b1111 @
b0 -
b1111000110000100 )
b1111000110000100 %
b0 !
14
#106
b11001101111000000010111001100100 1
b11001101111000000010111001100100 ;
#110
04
b1011 8
b111101000010001100110010001000 7
#111
b1000010010011110 3
b1000010010011110 :
b1001111001111010 2
b1001111001111010 9
b1000010010011110 5
#112
b1010010000110001011011101001100 6
#115
b1000010010011110 =
b1001111001111010 <
b11100100 >
b0 0
b1111110001100101 ,
b1111110001100101 (
b0 $
b111101000010001100110010001000 ?
b0 /
b0 +
b0 '
b0 #
b0 .
b0 *
b0 &
b0 "
b1111 @
b0 -
b0 )
b0 %
b0 !
14
#116
b111101000010001100110010001000 1
b111101000010001100110010001000 ;
#120
04
b1100 8
b1010010000110001011011101001100 7
#121
b1111101010110110 3
b1111101010110110 :
b100110000100101 2
b100110000100101 9
b1111101010110110 5
#122
b1001010100100100100010001001110 6
#125
b1111101010110110 =
b100110000100101 <
b110110000110 >
b110 0
b1010010110111001 ,
b1000010010011110 (
b10000100100111 $
b1010010000110001011011101001100 ?
b0 /
b100001001001111 +
b0 '
b100001001001111 #
b0 .
b1000010010011110 *
b1000010010011110 &
b0 "
b1111 @
b0 -
b0 )
b0 %
b0 !
14
#126
b1010010000110001011011101001100 1
b1010010000110001011011101001100 ;
#130
04
b1101 8
b1001010100100100100010001001110 7
#131
b111000101000111 3
b111000101000111 :
b1010011111101100 2
b1010011111101100 9
b111000101000111 5
#132
b1001010010011011011111001110100 6
#135
b111000101000111 =
b1010011111101100 <
b10000000000000 >
b10001000000100 0
b101100010101001 ,
b0 (
b110001000001101 $
b11101010100100 /
b1100010000011011 +
b1111101010110110 '
b11111010101101 #
b1001010100100100100010001001110 ?
b0 .
b111110101011011 *
b0 &
b111110101011011 "
b1111 @
b0 -
b1111101010110110 )
b1111101010110110 %
b0 !
14
#136
b1001010100100100100010001001110 1
b1001010100100100100010001001110 ;
#140
04
b1110 8
b1001010010011011011111001110100 7
#141
b1100101001000001 3
b1100101001000001 :
b1010100100100111 2
b1010100100100111 9
b1100101001000001 5
#142
b10000101101000111011100011100111 6
#145
b1100101001000001 =
b1010100100100111 <
b11000100000010 >
b11000000000011 0
b100100111100100 ,
b111000101000111 (
b11100010100011 $
b0 /
b111000101000111 +
b111000101000111 '
b0 #
b1001010010011011011111001110100 ?
b0 .
b0 *
b0 &
b0 "
b1111 @
b0 -
b0 )
b0 %
b0 !
14
#146
b1001010010011011011111001110100 1
b1001010010011011011111001110100 ;
#150
04
b1111 8
b10000101101000111011100011100111 7
#151
b1011001010010100 3
b1011001010010100 :
b110010100100111 2
b110010100100111 9
b1011001010010100 5
#152
b1000110100011111001100010001100 6
#155
b1011001010010100 =
b110010100100111 <
b111100001000000 >
b100001000000000 0
b10110011111000 ,
b0 (
b110111011111000 $
b100001000000000 /
b1101110111110001 +
b1100101001000001 '
b101011110110000 #
b100000000000000 .
b1010111101100001 *
b1100101001000001 &
b110010100100000 "
b1111 @
b10000101101000111011100011100111 ?
b0 -
b1100101001000001 )
b1100101001000001 %
b0 !
14
#156
b10000101101000111011100011100111 1
b10000101101000111011100011100111 ;
#160
04
b10000 8
b1000110100011111001100010001100 7
#161
b1001011111111011 3
b1001011111111011 :
b1110000001000100 2
b1110000001000100 9
b1001011111111011 5
#162
b10000101001000111111111010101100 6
#165
b1001011111111011 =
b1110000001000100 <
b11000000000000 >
b10000010000100 0
b101101100111001 ,
b0 (
b110101110111101 $
b11000010000100 /
b1101011101111011 +
b1011001010010100 '
b111010111101111 #
b1000000000000 .
b1110101111011110 *
b1011001010010100 &
b101100101001010 "
b1111 @
b1000110100011111001100010001100 ?
b0 -
b1011001010010100 )
b1011001010010100 %
b0 !
14
#166
b1000110100011111001100010001100 1
b1000110100011111001100010001100 ;
#170
04
b10001 8
b10000101001000111111111010101100 7
#171
b1000011101110100 3
b1000011101110100 :
b100111110001100 2
b100111110001100 9
b1000011101110100 5
#172
b101010000101101101111101110000 6
#175
b1000011101110100 =
b100111110001100 <
b111111111111000 >
b10000101001000111111111010101100 ?
b0 0
b100101111111101 ,
b0 (
b100101111111101 $
b0 /
b1001011111111011 +
b1001011111111011 '
b0 #
b0 .
b0 *
b0 &
b0 "
b1111 @
b0 -
b0 )
b0 %
b0 !
14
#176
b10000101001000111111111010101100 1
b10000101001000111111111010101100 ;
#180
04
b10010 8
b101010000101101101111101110000 7
#181
b100000100101011 3
b100000100101011 :
b1000110010110001 2
b1000110010110001 9
b100000100101011 5
#182
b100011110100001001001010111011 6
#185
b100000100101011 =
b1000110010110001 <
b10111000000 >
b1100110000 0
b1100010011001110 ,
b1000011101110100 (
b100001110111010 $
b101010000101101101111101110000 ?
b0 /
b1000011101110100 +
b1000011101110100 '
b0 #
b0 .
b0 *
b0 &
b0 "
b1111 @
b0 -
b0 )
b0 %
b0 !
14
#186
b101010000101101101111101110000 1
b101010000101101101111101110000 ;
#190
04
b10011 8
b100011110100001001001010111011 7
#191
b1010011111001101 3
b1010011111001101 :
b1000010100101010 2
b1000010100101010 9
b1010011111001101 5
#192
b1010111010010010000100010100010 6
#195
b1010011111001101 =
b1000010100101010 <
b101110 >
b0 0
b100000100101 ,
b0 (
b100000100101 $
b0 /
b1000001001010 +
b0 '
b1000001001010 #
b0 .
b10000010010101 *
b0 &
b10000010010101 "
b1111 @
b100011110100001001001010111011 ?
b0 -
b100000100101011 )
b100000100101011 %
b0 !
14
#196
b100011110100001001001010111011 1
b100011110100001001001010111011 ;
#200
04
b10100 8
b1010111010010010000100010100010 7
#201
b110011100111010 3
b110011100111010 :
b11001110101 2
b11001110101 9
b110011100111010 5
#202
b10100110101000100110000010 6
#205
b110011100111010 =
b11001110101 <
b10000100 >
b10000111000001 0
b1000111000111110 ,
b1010011111001101 (
b10100111110011 $
b0 /
b101001111100110 +
b0 '
b101001111100110 #
b0 .
b1010011111001101 *
b1010011111001101 &
b0 "
b1111 @
b1010111010010010000100010100010 ?
b0 -
b0 )
b0 %
b0 !
14
#206
b1010111010010010000100010100010 1
b1010111010010010000100010100010 ;
#210
04
b10101 8
b10100110101000100110000010 7
#211
b11011111011010 3
b11011111011010 :
b10010010111110 2
b10010010111110 9
b11011111011010 5
#212
b1000000001000001101111001100 6
#215
b11011111011010 =
b10010010111110 <
b0 >
b10100110101000100110000010 ?
b100001010 0
b11111001110000 ,
b0 (
b11111101111010 $
b100001010 /
b111111011110100 +
b110011100111010 '
b1100111001110 #
b0 .
b11001110011101 *
b0 &
b11001110011101 "
b1111 @
b0 -
b110011100111010 )
b110011100111010 %
b0 !
14
#216
b10100110101000100110000010 1
b10100110101000100110000010 ;
#220
04
b10110 8
b1000000001000001101111001100 7
#221
b11011001111000 3
b11011001111000 :
b110011101000001 2
b110011101000001 9
b11011001111000 5
#222
b10101111110000001110001111000 6
#225
b11011001111000 =
b110011101000001 <
b11111000010 >
b1011111011010 0
b11001000001001 ,
b11011111011010 (
b1011000011011 $
b1001111001000 /
b10110000110111 +
b11011111011010 '
b1101111101101 #
b1000000001000001101111001100 ?
b0 .
b11011111011010 *
b11011111011010 &
b0 "
b1111 @
b0 -
b0 )
b0 %
b0 !
14
#226
b1000000001000001101111001100 1
b1000000001000001101111001100 ;
#230
04
b10111 8
b10101111110000001110001111000 7
#231
b100001011100011 3
b100001011100011 :
b111010000000101 2
b111010000000101 9
b100001011100011 5
#232
b11110010100000010101001101111 6
#235
b100001011100011 =
b111010000000101 <
b0 >
b0 0
b11011001111 ,
b0 (
b11011001111 $
b10101111110000001110001111000 ?
b0 /
b110110011110 +
b0 '
b110110011110 #
b0 .
b1101100111100 *
b0 &
b1101100111100 "
b1111 @
b0 -
b11011001111000 )
b11011001111000 %
b0 !
14
#236
b10101111110000001110001111000 1
b10101111110000001110001111000 ;
#240
04
b11000 8
b11110010100000010101001101111 7
#241
b1000011101000001 3
b1000011101000001 :
b1100011111011010 2
b1100011111011010 9
b1000011101000001 5
#242
b1101001100101101011010001011010 6
#245
b1000011101000001 =
b1100011111011010 <
b110001111 >
b100000 0
b10100110001101 ,
b0 (
b10100100101101 $
b10100000 /
b101001001011011 +
b100001011100011 '
b1000010111000 #
b0 .
b10000101110001 *
b0 &
b10000101110001 "
b1111 @
b11110010100000010101001101111 ?
b0 -
b100001011100011 )
b100001011100011 %
b0 !
14
#246
b11110010100000010101001101111 1
b11110010100000010101001101111 ;
#250
04
b11001 8
b1101001100101101011010001011010 7
#251
b111111010011001 3
b111111010011001 :
b1010010101001011 2
b1010010101001011 9
b111111010011001 5
#252
b1010001101111011011001111010011 6
#255
b111111010011001 =
b1010010101001011 <
b11001000001 >
b101000000 0
b1010011010010001 ,
b1000011101000001 (
b10000111010000 $
b0 /
b100001110100000 +
b0 '
b100001110100000 #
b0 .
b1000011101000001 *
b1000011101000001 &
b0 "
b1111 @
b1101001100101101011010001011010 ?
b0 -
b0 )
b0 %
b0 !
14
#256
b1101001100101101011010001011010 1
b1101001100101101011010001011010 ;
#260
04
b11010 8
b1010001101111011011001111010011 7
#261
b1111111000110101 3
b1111111000110101 :
b1111011111011 2
b1111011111011 9
b1111111000110101 5
#262
b11110110000110111001111110111 6
#265
b1111111000110101 =
b1111011111011 <
b11110000000000 >
b10111000011001 0
b101000111100000 ,
b111111010011001 (
b111101110001 $
b10000000001000 /
b1111011100010 +
b0 '
b10000011101010 #
b11111000001000 .
b100000111010101 *
b111111010011001 &
b11111101001100 "
b1111 @
b1010001101111011011001111010011 ?
b0 -
b111111010011001 )
b111111010011001 %
b0 !
14
#266
b1010001101111011011001111010011 1
b1010001101111011011001111010011 ;
#270
04
b11011 8
b11110110000110111001111110111 7
#271
b111101001100001 3
b111101001100001 :
b1100011000111010 2
b1100011000111010 9
b111101001100001 5
#272
b1011110110000101011111111111010 6
#275
b111101001100001 =
b1100011000111010 <
b100000 >
b101111000010001 0
b1010000101100110 ,
b1111111000110101 (
b1111101000011 $
b11110110000110111001111110111 ?
b100000000010000 /
b11111010000111 +
b0 '
b100000010010111 #
b111111000010000 .
b1000000100101111 *
b1111111000110101 &
b111111100011010 "
b1111 @
b0 -
b1111111000110101 )
b1111111000110101 %
b0 !
14
#276
b11110110000110111001111110111 1
b11110110000110111001111110111 ;
#280
04
b11100 8
b1011110110000101011111111111010 7
#281
b1011011011001100 3
b1011011011001100 :
b110110111101011 2
b110110111101011 9
b1011011011001100 5
#282
b1001110011111001010100101000100 6
#285
b1011011011001100 =
b110110111101011 <
b10000001100001 >
b1101000000000 0
b110010011111001 ,
b111101001100001 (
b1111010011000 $
b0 /
b11110100110000 +
b0 '
b11110100110000 #
b0 .
b111101001100001 *
b111101001100001 &
b0 "
b1111 @
b1011110110000101011111111111010 ?
b0 -
b0 )
b0 %
b0 !
14
#286
b1011110110000101011111111111010 1
b1011110110000101011111111111010 ;
#290
04
b11101 8
b1001110011111001010100101000100 7
#291
b1111011101001110 3
b1111011101001110 :
b10011101010100 2
b10011101010100 9
b1111011101001110 5
#292
b100101111111100000011110011000 6
#295
b1111011101001110 =
b10011101010100 <
b10000000000000 >
b11001001001100 0
b1001011011000000 ,
b1011011011001100 (
b11001001001000 $
b1001001000100 /
b110010010010001 +
b0 '
b111011011010101 #
b1001110011111001010100101000100 ?
b1001001000100 .
b1110110110101010 *
b1011011011001100 &
b101101101100110 "
b1111 @
b0 -
b1011011011001100 )
b1011011011001100 %
b0 !
14
#296
b1001110011111001010100101000100 1
b1001110011111001010100101000100 ;
#300
04
b11110 8
b100101111111100000011110011000 7
#301
b1010010111110 3
b1010010111110 :
b1101110011011100 2
b1101110011011100 9
b1010010111110 5
#302
b10001111001010001101101001000 6
#305
b1010010111110 =
b1101110011011100 <
b0 >
b0 0
b111101110100111 ,
b0 (
b111101110100111 $
b100101111111100000011110011000 ?
b0 /
b1111011101001110 +
b1111011101001110 '
b0 #
b0 .
b0 *
b0 &
b0 "
b1111 @
b0 -
b0 )
b0 %
b0 !
14
#306
b100101111111100000011110011000 1
b100101111111100000011110011000 ;
#310
04
b11111 8
b10001111001010001101101001000 7
#311
b1110110110110001 3
b1110110110110001 :
b1010001010001111 2
b1010001010001111 9
b1110110110110001 5
#312
b10010110111011101100011111011111 6
#315
b1110110110110001 =
b1010001010001111 <
b110000111110 >
b10001111001010001101101001000 ?
b11110 0
b1111011100001 ,
b1010010111110 (
b101001011111 $
b0 /
b1010010111110 +
b1010010111110 '
b0 #
b0 .
b0 *
b0 &
b0 "
b1111 @
b0 -
b0 )
b0 %
b0 !
14
#316
b10001111001010001101101001000 1
b10001111001010001101101001000 ;
#320
04
b100000 8
b10010110111011101100011111011111 7
#321
b1100011011011000 3
b1100011011011000 :
b110101010100001 2
b110101010100001 9
b1100011011011000 5
#322
b1010010110100100111110111011000 6
#325
b1100011011011000 =
b110101010100001 <
b110100100000000 >
b110110110110000 0
b1110001001001011 ,
b1110110110110001 (
b110001001001010 $
b110110110110000 /
b1100010010010101 +
b1110110110110001 '
b100110110110100 #
b110010010010000 .
b1001101101101001 *
b1110110110110001 &
b111011011011000 "
b1111 @
b10010110111011101100011111011111 ?
b0 -
b1110110110110001 )
b1110110110110001 %
b0 !
14
#326
b10010110111011101100011111011111 1
b10010110111011101100011111011111 ;
#330
04
b100001 8
b1010010110100100111110111011000 7
#331
b1111100110011100 3
b1111100110011100 :
b10000000000101 2
b10000000000101 9
b1111100110011100 5
#332
b11111001110000110000000001100 6
#335
b1111100110011100 =
b10000000000101 <
b110000001000 >
b0 0
b1100011011011 ,
b0 (
b1100011011011 $
b0 /
b11000110110110 +
b0 '
b11000110110110 #
b0 .
b110001101101100 *
b0 &
b110001101101100 "
b1111 @
b1010010110100100111110111011000 ?
b0 -
b1100011011011000 )
b1100011011011000 %
b0 !
14
#336
b1010010110100100111110111011000 1
b1010010110100100111110111011000 ;
#340
04
b100010 8
b11111001110000110000000001100 7
#341
b1100010110111100 3
b1100010110111100 :
b1011111101111000 2
b1011111101111000 9
b1100010110111100 5
#342
b10010011111000111111010000100000 6
#345
b1100010110111100 =
b1011111101111000 <
b100 >
b10000000000100 0
b101101111111001 ,
b0 (
b110001111111101 $
b11111001110000110000000001100 ?
b11100000000100 /
b1100011111111011 +
b1111100110011100 '
b11111001100111 #
b0 .
b111110011001110 *
b0 &
b111110011001110 "
b1111 @
b0 -
b1111100110011100 )
b1111100110011100 %
b0 !
14
#346
b11111001110000110000000001100 1
b11111001110000110000000001100 ;
#350
04
b100011 8
b10010011111000111111010000100000 7
#351
b11000100001010 3
b11000100001010 :
b1110101101 2
b1110101101 9
b11000100001010 5
#352
b101101000100000111000010 6
#355
b11000100001010 =
b1110101101 <
b100110000111000 >
b0 0
b1100010110111100 ,
b1100010110111100 (
b0 $
b10010011111000111111010000100000 ?
b0 /
b0 +
b0 '
b0 #
b0 .
b0 *
b0 &
b0 "
b1111 @
b0 -
b0 )
b0 %
b0 !
14
#356
b10010011111000111111010000100000 1
b10010011111000111111010000100000 ;
#360
04
b100100 8
b101101000100000111000010 7
#361
b1001011010101101 3
b1001011010101101 :
b1010101110000001 2
b1010101110000001 9
b1001011010101101 5
#362
b1100100111100010111110000101101 6
