Ch05-RTL/Multiplier-Array/Pipelined-0/multiplier-Pipelined-0-128b.v
module multiplier(a, b, y, clk);

   parameter width = 128;
   input [width-1:0] a, b;
   output [2*width-1:0] y;
   // output  y;
   input 	      clk;

   reg [width-1:0]    areg, breg;
   reg [2*width-1:0]    partials [width-1:0];
   

   // genvar 		  i;
   // assign partials[width-1 : 0] = a[0] ? b : 0;
   // generate for (i = 1; i < width; i = i+1) begin:gen
   //    assign partials[width*(i+1)-1 : width*i] = (a[i] ? b << i : 0) +
   // 						 partials[width*i-1 : width*(i-1)];
   // end endgenerate

   // assign y = partials[width*width-1 : width*(width-1)];

   integer 	      i;



   // Input registers:
   always @(posedge clk) begin
      areg = a;
      breg = b;
   end

   // No pipelining:   
   always @(posedge clk) begin

      partials[0] = areg[0] ? breg : 0;

      for (i = 1; i < width; i = i+1) begin
   	 partials[i] = (areg[i] ? breg << i : 0) +
   	       partials[i-1];
      end

   end

   
   assign #1 y = (partials[width-1]);
   
   
endmodule // multiplier

Ch05-RTL/Multiplier-Array/Pipelined-0/multiplier_tb.v

module multiplier_tb;

   parameter width = 64;
   
   reg [width-1:0] a, b;
   wire [2*width-1:0] y;
   reg [2*width-1:0]  yfull;
   reg [2*width-1:0]  yprev[width-1:0];
   
   
   reg 	       clk;
   
   
   multiplier #(
		.width(width)
		) uut (
		       .a(a),
		       .b(b),
		       .y(y),
		       .clk(clk)
		       ); 

   reg [width-1:0]  xrnd = 11;
   task xorshift32;
      begin
	 xrnd = xrnd ^ (xrnd << (width*3/3)-1);
	 xrnd = xrnd ^ (xrnd >> (width/2)+1);
	 xrnd = xrnd ^ (xrnd << (width*3/4)-1);
	 xrnd = xrnd ^ (xrnd >> (width*3/3)-1);
      end endtask

   integer i,j;

   always #5 clk = ~clk;
   
   initial begin
      $dumpfile("multiplier_tb.vcd");
      // $dumpvars(1,multiplier_tb.uut.preg[0]);
      // $dumpvars(1,multiplier_tb.uut.preg[1]);
      // $dumpvars(1,multiplier_tb.uut.preg[2]);
      // $dumpvars(1,multiplier_tb.uut.preg[3]);
      // // $dumpvars(1,multiplier_tb.uut.partialsa[3]);

      // $dumpvars(1,multiplier_tb.uut.partials[0]);
      // $dumpvars(1,multiplier_tb.uut.partials[1]);
      // $dumpvars(1,multiplier_tb.uut.partials[2]);
      // $dumpvars(1,multiplier_tb.uut.partials[3]);

      // $dumpvars(1,multiplier_tb.uut.partialss[0]);
      // $dumpvars(1,multiplier_tb.uut.partialss[1]);
      // $dumpvars(1,multiplier_tb.uut.partialss[2]);    
      // $dumpvars(1,multiplier_tb.uut.partialss[3]);

      // $dumpvars(1,multiplier_tb.uut.partialsco[0]);
      // $dumpvars(1,multiplier_tb.uut.partialsco[1]);
      // $dumpvars(1,multiplier_tb.uut.partialsco[2]);
      // $dumpvars(1,multiplier_tb.uut.partialsco[3]);
      // $dumpvars(1,multiplier_tb.uut.preg[3]);
      // $dumpvars(1,multiplier_tb.uut.preg[5]);
      // $dumpvars(1,multiplier_tb.uut.preg[7]);
      $dumpvars(0, multiplier_tb);
 
      clk = 1'b0;
      
      for (i = 0; i < 20; i = i+1)
	begin
	   #2;

	   xorshift32;
	   a <= xrnd;
	   xorshift32;
	   b <= xrnd;

	   // if (i == 0) begin
	   //    a <= 4'b1101;
	   //    b <= 1;
	   // end
	   // else if (i == 1) begin
	   //    a <= 4'b1001;
	   //    b <= i;
	   // end
	   // else begin
	   //    a <= 4'b1111;
	   //    b <= i;
	   // end
	   	   
	   #1;
	   
	   yfull = a*b;
	   #7;

	   $display("%d * %d = %d (%d, Prev 0: %d)", a, b, y, yfull, yprev[0]);
	   if (y != yprev[0]) begin
	      $display("ERROR!");
	      // $finish;
	   end
	    for (j=width-1; j>0; j=j-1) begin
	      yprev[j] = yprev[j-1];
	   end
	   yprev[0] = yfull;
	   
	end // for (i = 0; i < 100; i = i+1)

      a = 8'b11111111;
      b = 8'b11111111;

      #5;
      
      $display("PASSED.");
      $finish;
      
   end

endmodule

Ch05-RTL/Multiplier-Array/Pipelined-0/dump.vcd
$date
	Mon Jul 13 08:58:25 2020
$end
$version
	Icarus Verilog
$end
$timescale
	1s
$end
$scope module multiplier_tb $end
$var wire 8 ! y [7:0] $end
$var reg 4 " a [3:0] $end
$var reg 4 # b [3:0] $end
$var reg 1 $ clk $end
$var reg 4 % xrnd [3:0] $end
$var reg 8 & yfull [7:0] $end
$var integer 32 ' i [31:0] $end
$var integer 32 ( j [31:0] $end
$scope module uut $end
$var wire 4 ) a [3:0] $end
$var wire 4 * b [3:0] $end
$var wire 1 $ clk $end
$var wire 8 + y [7:0] $end
$var reg 4 , areg [3:0] $end
$var reg 4 - breg [3:0] $end
$var integer 32 . i [31:0] $end
$upscope $end
$scope task xorshift32 $end
$upscope $end
$upscope $end
$enddefinitions $end
#0
$dumpvars
bx .
bx -
bx ,
bx +
bx *
bx )
bx (
b0 '
bx &
b1011 %
0$
bx #
bx "
bx !
$end
#2
b11 #
b11 *
b1110 "
b1110 )
b11 %
#3
b101010 &
#5
b11 -
b1110 ,
b100 .
1$
#10
0$
b1 '
b0 (
#12
b1011 #
b1011 *
b10 "
b10 )
b1011 %
#13
b10110 &
#15
b100 .
b1011 -
b10 ,
1$
#16
b10110 !
b10110 +
#20
0$
b10 '
b0 (
#22
b11 #
b11 *
b1110 "
b1110 )
b11 %
#23
b101010 &
#25
b11 -
b1110 ,
b100 .
1$
#30
0$
b11 '
b0 (
#32
b1011 #
b1011 *
b10 "
b10 )
b1011 %
#33
b10110 &
#35
b100 .
b1011 -
b10 ,
1$
#40
0$
b100 '
b0 (
#42
b11 #
b11 *
b1110 "
b1110 )
b11 %
#43
b101010 &
#45
b11 -
b1110 ,
b100 .
1$
#50
0$
b101 '
b0 (
#52
b1011 #
b1011 *
b10 "
b10 )
b1011 %
#53
b10110 &
#55
b100 .
b1011 -
b10 ,
1$
#60
0$
b110 '
b0 (
#62
b11 #
b11 *
b1110 "
b1110 )
b11 %
#63
b101010 &
#65
b11 -
b1110 ,
b100 .
1$
#70
0$
b111 '
b0 (
#72
b1011 #
b1011 *
b10 "
b10 )
b1011 %
#73
b10110 &
#75
b100 .
b1011 -
b10 ,
1$
#80
0$
b1000 '
b0 (
#82
b11 #
b11 *
b1110 "
b1110 )
b11 %
#83
b101010 &
#85
b11 -
b1110 ,
b100 .
1$
#90
0$
b1001 '
b0 (
#92
b1011 #
b1011 *
b10 "
b10 )
b1011 %
#93
b10110 &
#95
b100 .
b1011 -
b10 ,
1$
#100
0$
b1010 '
b0 (
#102
b11 #
b11 *
b1110 "
b1110 )
b11 %
#103
b101010 &
#105
b11 -
b1110 ,
b100 .
1$
#110
0$
b1011 '
b0 (
#112
b1011 #
b1011 *
b10 "
b10 )
b1011 %
#113
b10110 &
#115
b100 .
b1011 -
b10 ,
1$
#120
0$
b1100 '
b0 (
#122
b11 #
b11 *
b1110 "
b1110 )
b11 %
#123
b101010 &
#125
b11 -
b1110 ,
b100 .
1$
#130
0$
b1101 '
b0 (
#132
b1011 #
b1011 *
b10 "
b10 )
b1011 %
#133
b10110 &
#135
b100 .
b1011 -
b10 ,
1$
#140
0$
b1110 '
b0 (
#142
b11 #
b11 *
b1110 "
b1110 )
b11 %
#143
b101010 &
#145
b11 -
b1110 ,
b100 .
1$
#150
0$
b1111 '
b0 (
#152
b1011 #
b1011 *
b10 "
b10 )
b1011 %
#153
b10110 &
#155
b100 .
b1011 -
b10 ,
1$
#160
0$
b10000 '
b0 (
#162
b11 #
b11 *
b1110 "
b1110 )
b11 %
#163
b101010 &
#165
b11 -
b1110 ,
b100 .
1$
#170
0$
b10001 '
b0 (
#172
b1011 #
b1011 *
b10 "
b10 )
b1011 %
#173
b10110 &
#175
b100 .
b1011 -
b10 ,
1$
#180
0$
b10010 '
b0 (
#182
b11 #
b11 *
b1110 "
b1110 )
b11 %
#183
b101010 &
#185
b11 -
b1110 ,
b100 .
1$
#190
0$
b10011 '
b0 (
#192
b1011 #
b1011 *
b10 "
b10 )
b1011 %
#193
b10110 &
#195
b100 .
b1011 -
b10 ,
1$
#200
0$
b1111 #
b1111 *
b1111 "
b1111 )
b10100 '
b0 (
#205
b1111 -
b1111 ,
b100 .
1$
