Ch03-ModelingBasics/ParityGenerator/pargen.v

// Parity generator
//
module pargen (a, b, c, pout);
   input a, b, c;
   output pout;
   reg 	  pout;

   always @ (a,b,c)
     begin
	case ({a,b,c})
	  3'b000: pout = 1'b1;
	  3'b001: pout = 1'b0;
	  3'b010: pout = 1'b0;
	  3'b011: pout = 1'b1;
	  3'b100: pout = 1'b0;
	  3'b101: pout = 1'b1;
	  3'b110: pout = 1'b1;
	  3'b111: pout = 1'b0;
	  default: pout = 1'bx;
	endcase
     end
endmodule // pargen

Ch03-ModelingBasics/ParityGenerator/pargen_tb.v

`timescale 100ps/10ps      // Unit of time is 100ps

module pargen_tb();
   reg a, b, c;        // Input stimuli
   wire y;  // Output of DuT

   // Instantiate designs under test:
   pargen dut (.a(a), .b(b), .c(c), .pout(y));
   
   initial begin
      $dumpfile("pargen.vcd"); // File with simulation results
      $dumpvars(0,pargen_tb);

      // Stimuli generator:
      #10 a=1'b0; b=1'b0; c=1'b0;
      #10 a=1'b0; b=1'b0; c=1'b1;
      #10 a=1'b0; b=1'b1; c=1'b0;
      #10 a=1'b0; b=1'b1; c=1'b1;
      #10 a=1'b1; b=1'b0; c=1'b0;
      #10 a=1'b1; b=1'b0; c=1'b1;
      #10 a=1'b1; b=1'b1; c=1'b0;
      #10 a=1'b1; b=1'b1; c=1'b1;

      #10 $finish;                  // Finish simulation
   end 

endmodule

Ch03-ModelingBasics/ParityGenerator/pargen.vcd
$date
	Sat Sep 12 17:17:59 2020
$end
$version
	Icarus Verilog
$end
$timescale
	10ps
$end
$scope module pargen_tb $end
$var wire 1 ! y $end
$var reg 1 " a $end
$var reg 1 # b $end
$var reg 1 $ c $end
$scope module dut $end
$var wire 1 " a $end
$var wire 1 # b $end
$var wire 1 $ c $end
$var reg 1 ! pout $end
$upscope $end
$upscope $end
$enddefinitions $end
#0
$dumpvars
x$
x#
x"
x!
$end
#100
1!
0$
0#
0"
#200
0!
1$
#300
0$
1#
#400
1!
1$
#500
0!
0$
0#
1"
#600
1!
1$
#700
0$
1#
#800
0!
1$
