Ch04-LatchesDelays/Delays/sdelay.v

`timescale 1ns/100ps

//
// 
module sdelay (a, yblhs, ybrhs, ynblhs, ynbrhs, ycbl);
   output reg yblhs, ybrhs, ynblhs, ynbrhs;
   output ycbl;
   input a;

   always @(a)
     #4 yblhs = ~a;

   always @(a)
     ybrhs = #4 ~a;

   always @(a)
     #4 ynblhs <= ~a;

   always @(a)
     ynbrhs <= #4 ~a;

   assign #4 ycbl = ~a;
   // assign ycbr = #4 ~a;
   //  assign #4 ycnbl <= ~a;
   // assign ycnbl <= #4 ~a;
   
endmodule

Ch04-LatchesDelays/Delays/sdelay_tb.v

`timescale 1ns/100ps

module sdelay_tb ();
   reg a;
   wire yblhs, ybrhs, ynblhs, ynbrhs, ycbl;
   
   sdelay  uu1 (.a(a), .yblhs(yblhs), .ybrhs(ybrhs), .ynblhs(ynblhs), .ynbrhs(ynbrhs), .ycbl(ycbl));
   
   initial begin
      $dumpfile("sdelay.vcd");
      $dumpvars(0,sdelay_tb);

      a = 1'b0;
      #5 a = 1'b1;
      #15 a = 1'b0;
      #3 a = 1'b1;
      #1 a = 1'b0;
      #1 a = 1'b1;
      #1 a = 1'b0;
      #7 a = 1'b1;

      #10 $finish;

   end // initial begin
endmodule

Ch04-LatchesDelays/Delays/sdelay.vcd
$date
	Thu Sep 24 10:50:09 2020
$end
$version
	Icarus Verilog
$end
$timescale
	100ps
$end
$scope module sdelay_tb $end
$var wire 1 ! ynbrhs $end
$var wire 1 " ynblhs $end
$var wire 1 # ycbl $end
$var wire 1 $ ybrhs $end
$var wire 1 % yblhs $end
$var reg 1 & a $end
$scope module uu1 $end
$var wire 1 & a $end
$var wire 1 # ycbl $end
$var reg 1 % yblhs $end
$var reg 1 $ ybrhs $end
$var reg 1 " ynblhs $end
$var reg 1 ! ynbrhs $end
$upscope $end
$upscope $end
$enddefinitions $end
#0
$dumpvars
0&
x%
x$
x#
x"
x!
$end
#40
1"
1!
1#
1$
1%
#50
1&
#90
0"
0!
0#
0%
0$
#200
0&
#230
1&
#240
1!
0&
1$
#250
1&
#260
0&
#270
0!
#280
1"
1!
1%
#290
0!
#300
1!
1#
#330
1&
#370
0"
0!
0#
0$
0%
